[{"timestamp":{"iso":"2009-07-05T08:40:06","unixtimestamp":1246783206},"track":{"name":"Midnight Marauders Tour Guide","mbid":"2a17502b-4acc-49ab-9749-541a08ecf3e3","artist":{"name":"A Tribe Called Quest","mbid":"9689aa5a-4471-4fb4-9721-07cecda0fa9f"}},"uncorrectedTrack":{"name":"Midnight Marauders Tour Guide","artist":{"name":"Tribe Called Quest"}},"album":{"name":"Midnight Marauders","artist":{"name":"Tribe Called Quest"}}},{"timestamp":{"iso":"2009-07-05T08:40:51","unixtimestamp":1246783251},"track":{"name":"Steve Biko (Stir It Up)","mbid":"0fecd2c2-2f47-4d94-a34a-af0d505e87f5","artist":{"name":"A Tribe Called Quest","mbid":"9689aa5a-4471-4fb4-9721-07cecda0fa9f"}},"uncorrectedTrack":{"name":"Steve Biko (Stir It Up)","artist":{"name":"Tribe Called Quest"}},"album":{"name":"Midnight Marauders","artist":{"name":"Tribe Called Quest"}}},{"timestamp":{"iso":"2009-07-05T08:44:02","unixtimestamp":1246783442},"track":{"name":"Award Tour","mbid":"21749172-7f34-4fec-924a-0761dfcc1a6d","artist":{"name":"A Tribe Called Quest","mbid":"9689aa5a-4471-4fb4-9721-07cecda0fa9f"}},"uncorrectedTrack":{"name":"Award Tour","artist":{"name":"Tribe Called Quest"}},"album":{"name":"Midnight Marauders","artist":{"name":"Tribe Called Quest"}}},{"timestamp":{"iso":"2009-07-05T08:47:49","unixtimestamp":1246783669},"track":{"name":"8 Million Stories","mbid":"26641c50-85fd-48c8-ac0b-5d019f7fba23","artist":{"name":"A Tribe Called Quest","mbid":"9689aa5a-4471-4fb4-9721-07cecda0fa9f"}},"uncorrectedTrack":{"name":"8 Million Stories","artist":{"name":"Tribe Called Quest"}},"album":{"name":"Midnight Marauders","artist":{"name":"Tribe Called Quest"}}},{"timestamp":{"iso":"2009-07-05T08:52:11","unixtimestamp":1246783931},"track":{"name":"Sucka Nigga","mbid":"237fde6a-ebfd-44b2-b8f5-23edc22f55a0","artist":{"name":"A Tribe Called Quest","mbid":"9689aa5a-4471-4fb4-9721-07cecda0fa9f"}},"uncorrectedTrack":{"name":"Sucka Nigga","artist":{"name":"Tribe Called Quest"}},"album":{"name":"Midnight Marauders","artist":{"name":"Tribe Called Quest"}}},{"timestamp":{"iso":"2009-07-05T08:56:17","unixtimestamp":1246784177},"track":{"name":"Midnight","mbid":"026439a0-1365-413e-b2f7-1d597caaac1c","artist":{"name":"A Tribe Called Quest","mbid":"9689aa5a-4471-4fb4-9721-07cecda0fa9f"}},"uncorrectedTrack":{"name":"Midnight","artist":{"name":"Tribe Called Quest"}},"album":{"name":"Midnight Marauders","artist":{"name":"Tribe Called Quest"}}},{"timestamp":{"iso":"2009-07-05T09:21:36","unixtimestamp":1246785696},"track":{"name":"We Can Get Down","mbid":"2e6fa81a-0fa0-4bed-a43a-a9d6b99fedc8","artist":{"name":"A Tribe Called Quest","mbid":"9689aa5a-4471-4fb4-9721-07cecda0fa9f"}},"uncorrectedTrack":{"name":"We Can Get Down","artist":{"name":"Tribe Called Quest"}},"album":{"name":"Midnight Marauders","artist":{"name":"Tribe Called Quest"}}},{"timestamp":{"iso":"2009-07-05T09:25:55","unixtimestamp":1246785955},"track":{"name":"Electric Relaxation","mbid":"4b66d95b-8943-47c6-b3e5-cba71de88652","artist":{"name":"A Tribe Called Quest","mbid":"9689aa5a-4471-4fb4-9721-07cecda0fa9f"}},"uncorrectedTrack":{"name":"Electric Relaxation","artist":{"name":"Tribe Called Quest"}},"album":{"name":"Midnight Marauders","artist":{"name":"Tribe Called Quest"}}},{"timestamp":{"iso":"2009-07-05T09:29:59","unixtimestamp":1246786199},"track":{"name":"Clap Your Hands","mbid":"1e64d2bc-185d-4ffb-a2e4-820e531581ed","artist":{"name":"A Tribe Called Quest","mbid":"9689aa5a-4471-4fb4-9721-07cecda0fa9f"}},"uncorrectedTrack":{"name":"Clap Your Hands","artist":{"name":"Tribe Called Quest"}},"album":{"name":"Midnight Marauders","artist":{"name":"Tribe Called Quest"}}},{"timestamp":{"iso":"2009-07-05T09:33:15","unixtimestamp":1246786395},"track":{"name":"Oh My God","mbid":"2caa1e9c-5ecb-4ef8-a781-135517357022","artist":{"name":"A Tribe Called Quest","mbid":"9689aa5a-4471-4fb4-9721-07cecda0fa9f"}},"uncorrectedTrack":{"name":"Oh My God","artist":{"name":"Tribe Called Quest"}},"album":{"name":"Midnight Marauders","artist":{"name":"Tribe Called Quest"}}},{"timestamp":{"iso":"2009-07-05T09:36:46","unixtimestamp":1246786606},"track":{"name":"Keep It Rollin\u0027","mbid":"63b02d33-96f5-472b-bddb-217b647b6831","artist":{"name":"A Tribe Called Quest","mbid":"9689aa5a-4471-4fb4-9721-07cecda0fa9f"}},"uncorrectedTrack":{"name":"Keep It Rollin\u0027","artist":{"name":"Tribe Called Quest"}},"album":{"name":"Midnight Marauders","artist":{"name":"Tribe Called Quest"}}},{"timestamp":{"iso":"2009-07-05T09:39:53","unixtimestamp":1246786793},"track":{"name":"The Chase, Part II","mbid":"6fb10da0-77cd-4190-a4c4-b128cee80205","artist":{"name":"A Tribe Called Quest","mbid":"9689aa5a-4471-4fb4-9721-07cecda0fa9f"}},"uncorrectedTrack":{"name":"The Chase, Part II","artist":{"name":"Tribe Called Quest"}},"album":{"name":"Midnight Marauders","artist":{"name":"Tribe Called Quest"}}},{"timestamp":{"iso":"2009-07-05T09:43:55","unixtimestamp":1246787035},"track":{"name":"Lyrics to Go","mbid":"3c93ea03-cc76-4a44-b155-7531ef7230a3","artist":{"name":"A Tribe Called Quest","mbid":"9689aa5a-4471-4fb4-9721-07cecda0fa9f"}},"uncorrectedTrack":{"name":"Lyrics to Go","mbid":"3c93ea03-cc76-4a44-b155-7531ef7230a3","artist":{"name":"A Tribe Called Quest","mbid":"9689aa5a-4471-4fb4-9721-07cecda0fa9f"}},"album":{"name":"Midnight Marauders","mbid":"66970091-71ab-47a6-a62a-30ee44109fae","artist":{"name":"A Tribe Called Quest","mbid":"9689aa5a-4471-4fb4-9721-07cecda0fa9f"}}},{"timestamp":{"iso":"2009-07-05T09:48:05","unixtimestamp":1246787285},"track":{"name":"God Lives Through","mbid":"0ee026d4-f187-488a-b721-9367dd488782","artist":{"name":"A Tribe Called Quest","mbid":"9689aa5a-4471-4fb4-9721-07cecda0fa9f"}},"uncorrectedTrack":{"name":"God Lives Through","mbid":"0ee026d4-f187-488a-b721-9367dd488782","artist":{"name":"A Tribe Called Quest","mbid":"9689aa5a-4471-4fb4-9721-07cecda0fa9f"}},"album":{"name":"Midnight Marauders","mbid":"66970091-71ab-47a6-a62a-30ee44109fae","artist":{"name":"A Tribe Called Quest","mbid":"9689aa5a-4471-4fb4-9721-07cecda0fa9f"}}},{"timestamp":{"iso":"2009-07-05T09:52:20","unixtimestamp":1246787540},"track":{"name":"Hot Sex","mbid":"03f517c7-0946-47ee-b560-48a741acd5ff","artist":{"name":"A Tribe Called Quest","mbid":"9689aa5a-4471-4fb4-9721-07cecda0fa9f"}},"uncorrectedTrack":{"name":"Hot Sex","artist":{"name":"Tribe Called Quest"}},"album":{"name":"Midnight Marauders","artist":{"name":"Tribe Called Quest"}}},{"timestamp":{"iso":"2009-07-05T21:14:35","unixtimestamp":1246828475},"track":{"name":"5 am","mbid":"42f2f002-69db-4c99-925a-8a68104362c3","artist":{"name":"9 Lazy 9","mbid":"511481ee-1b97-4333-a161-0492f3e1303c"}},"uncorrectedTrack":{"name":"5 am","mbid":"42f2f002-69db-4c99-925a-8a68104362c3","artist":{"name":"9 Lazy 9","mbid":"511481ee-1b97-4333-a161-0492f3e1303c"}},"album":{"name":"Paradise Blown","mbid":"0321d916-5799-4eaf-aabc-70fac210465e","artist":{"name":"9 Lazy 9","mbid":"511481ee-1b97-4333-a161-0492f3e1303c"}}},{"timestamp":{"iso":"2009-07-05T21:20:00","unixtimestamp":1246828800},"track":{"name":"Shak","mbid":"109bbeb2-2d27-4420-b412-d2f37bf401ba","artist":{"name":"9 Lazy 9","mbid":"511481ee-1b97-4333-a161-0492f3e1303c"}},"uncorrectedTrack":{"name":"Shak","mbid":"109bbeb2-2d27-4420-b412-d2f37bf401ba","artist":{"name":"9 Lazy 9","mbid":"511481ee-1b97-4333-a161-0492f3e1303c"}},"album":{"name":"Paradise Blown","mbid":"0321d916-5799-4eaf-aabc-70fac210465e","artist":{"name":"9 Lazy 9","mbid":"511481ee-1b97-4333-a161-0492f3e1303c"}}},{"timestamp":{"iso":"2009-07-05T21:24:16","unixtimestamp":1246829056},"track":{"name":"Turn Me Loose","mbid":"8c167df3-b826-472a-b181-e2253c6250b5","artist":{"name":"9 Lazy 9","mbid":"511481ee-1b97-4333-a161-0492f3e1303c"}},"uncorrectedTrack":{"name":"Turn Me Loose","mbid":"8c167df3-b826-472a-b181-e2253c6250b5","artist":{"name":"9 Lazy 9","mbid":"511481ee-1b97-4333-a161-0492f3e1303c"}},"album":{"name":"Paradise Blown","mbid":"0321d916-5799-4eaf-aabc-70fac210465e","artist":{"name":"9 Lazy 9","mbid":"511481ee-1b97-4333-a161-0492f3e1303c"}}},{"timestamp":{"iso":"2009-07-05T21:28:38","unixtimestamp":1246829318},"track":{"name":"Black Jesus","mbid":"f5c6150f-140f-4761-a684-f4eb341a2c7b","artist":{"name":"9 Lazy 9","mbid":"511481ee-1b97-4333-a161-0492f3e1303c"}},"uncorrectedTrack":{"name":"Black Jesus","mbid":"f5c6150f-140f-4761-a684-f4eb341a2c7b","artist":{"name":"9 Lazy 9","mbid":"511481ee-1b97-4333-a161-0492f3e1303c"}},"album":{"name":"Paradise Blown","mbid":"0321d916-5799-4eaf-aabc-70fac210465e","artist":{"name":"9 Lazy 9","mbid":"511481ee-1b97-4333-a161-0492f3e1303c"}}},{"timestamp":{"iso":"2009-07-05T21:32:44","unixtimestamp":1246829564},"track":{"name":"All Aboard","mbid":"25bcf95b-e750-4cb7-810d-a5e6c291e4fa","artist":{"name":"9 Lazy 9","mbid":"511481ee-1b97-4333-a161-0492f3e1303c"}},"uncorrectedTrack":{"name":"All Aboard","mbid":"25bcf95b-e750-4cb7-810d-a5e6c291e4fa","artist":{"name":"9 Lazy 9","mbid":"511481ee-1b97-4333-a161-0492f3e1303c"}},"album":{"name":"Paradise Blown","mbid":"0321d916-5799-4eaf-aabc-70fac210465e","artist":{"name":"9 Lazy 9","mbid":"511481ee-1b97-4333-a161-0492f3e1303c"}}},{"timestamp":{"iso":"2009-07-05T21:35:51","unixtimestamp":1246829751},"track":{"name":"Summer","mbid":"3ce4c703-7092-444e-926a-5b91b6e7f17f","artist":{"name":"9 Lazy 9","mbid":"511481ee-1b97-4333-a161-0492f3e1303c"}},"uncorrectedTrack":{"name":"Summer","mbid":"3ce4c703-7092-444e-926a-5b91b6e7f17f","artist":{"name":"9 Lazy 9","mbid":"511481ee-1b97-4333-a161-0492f3e1303c"}},"album":{"name":"Paradise Blown","mbid":"0321d916-5799-4eaf-aabc-70fac210465e","artist":{"name":"9 Lazy 9","mbid":"511481ee-1b97-4333-a161-0492f3e1303c"}}},{"timestamp":{"iso":"2009-07-05T21:39:46","unixtimestamp":1246829986},"track":{"name":"The Herb","mbid":"086338a0-e939-44bf-8b48-9d73f6d0c9a7","artist":{"name":"9 Lazy 9","mbid":"511481ee-1b97-4333-a161-0492f3e1303c"}},"uncorrectedTrack":{"name":"The Herb","mbid":"086338a0-e939-44bf-8b48-9d73f6d0c9a7","artist":{"name":"9 Lazy 9","mbid":"511481ee-1b97-4333-a161-0492f3e1303c"}},"album":{"name":"Paradise Blown","mbid":"0321d916-5799-4eaf-aabc-70fac210465e","artist":{"name":"9 Lazy 9","mbid":"511481ee-1b97-4333-a161-0492f3e1303c"}}},{"timestamp":{"iso":"2009-07-05T21:44:57","unixtimestamp":1246830297},"track":{"name":"Brothers of the Red","mbid":"44ed91ec-b71f-4a01-956e-b03ea5b26fd7","artist":{"name":"9 Lazy 9","mbid":"511481ee-1b97-4333-a161-0492f3e1303c"}},"uncorrectedTrack":{"name":"Brothers of the Red","mbid":"44ed91ec-b71f-4a01-956e-b03ea5b26fd7","artist":{"name":"9 Lazy 9","mbid":"511481ee-1b97-4333-a161-0492f3e1303c"}},"album":{"name":"Paradise Blown","mbid":"0321d916-5799-4eaf-aabc-70fac210465e","artist":{"name":"9 Lazy 9","mbid":"511481ee-1b97-4333-a161-0492f3e1303c"}}},{"timestamp":{"iso":"2009-07-05T21:49:55","unixtimestamp":1246830595},"track":{"name":"Take Nine","mbid":"34b9ba41-91d9-4a66-b045-c2d4bbbb2f97","artist":{"name":"9 Lazy 9","mbid":"511481ee-1b97-4333-a161-0492f3e1303c"}},"uncorrectedTrack":{"name":"Take Nine","mbid":"34b9ba41-91d9-4a66-b045-c2d4bbbb2f97","artist":{"name":"9 Lazy 9","mbid":"511481ee-1b97-4333-a161-0492f3e1303c"}},"album":{"name":"Paradise Blown","mbid":"0321d916-5799-4eaf-aabc-70fac210465e","artist":{"name":"9 Lazy 9","mbid":"511481ee-1b97-4333-a161-0492f3e1303c"}}},{"timestamp":{"iso":"2009-07-05T21:55:41","unixtimestamp":1246830941},"track":{"name":"Spoonful of Slow","mbid":"2cdddc24-d820-4164-8ec9-f73f82bb1048","artist":{"name":"9 Lazy 9","mbid":"511481ee-1b97-4333-a161-0492f3e1303c"}},"uncorrectedTrack":{"name":"Spoonful of Slow","mbid":"2cdddc24-d820-4164-8ec9-f73f82bb1048","artist":{"name":"9 Lazy 9","mbid":"511481ee-1b97-4333-a161-0492f3e1303c"}},"album":{"name":"Paradise Blown","mbid":"0321d916-5799-4eaf-aabc-70fac210465e","artist":{"name":"9 Lazy 9","mbid":"511481ee-1b97-4333-a161-0492f3e1303c"}}},{"timestamp":{"iso":"2009-07-05T21:58:30","unixtimestamp":1246831110},"track":{"name":"Bad Boy","mbid":"377f398a-bcec-4851-a043-c0f5b4c64cbf","artist":{"name":"9 Lazy 9","mbid":"511481ee-1b97-4333-a161-0492f3e1303c"}},"uncorrectedTrack":{"name":"Bad Boy","mbid":"377f398a-bcec-4851-a043-c0f5b4c64cbf","artist":{"name":"9 Lazy 9","mbid":"511481ee-1b97-4333-a161-0492f3e1303c"}},"album":{"name":"Paradise Blown","mbid":"0321d916-5799-4eaf-aabc-70fac210465e","artist":{"name":"9 Lazy 9","mbid":"511481ee-1b97-4333-a161-0492f3e1303c"}}},{"timestamp":{"iso":"2009-07-05T22:02:40","unixtimestamp":1246831360},"track":{"name":"Not Nice","mbid":"360a6d71-1f04-43de-8d3c-f19ccaf3372f","artist":{"name":"9 Lazy 9","mbid":"511481ee-1b97-4333-a161-0492f3e1303c"}},"uncorrectedTrack":{"name":"Not Nice","mbid":"360a6d71-1f04-43de-8d3c-f19ccaf3372f","artist":{"name":"9 Lazy 9","mbid":"511481ee-1b97-4333-a161-0492f3e1303c"}},"album":{"name":"Paradise Blown","mbid":"0321d916-5799-4eaf-aabc-70fac210465e","artist":{"name":"9 Lazy 9","mbid":"511481ee-1b97-4333-a161-0492f3e1303c"}}},{"timestamp":{"iso":"2009-07-05T22:07:31","unixtimestamp":1246831651},"track":{"name":"Interleud","mbid":"b6287d49-f7ae-4298-96f9-f211c6d90bc0","artist":{"name":"9 Lazy 9","mbid":"511481ee-1b97-4333-a161-0492f3e1303c"}},"uncorrectedTrack":{"name":"Interlude","artist":{"name":"9 Lazy 9","mbid":"511481ee-1b97-4333-a161-0492f3e1303c"}},"album":{"name":"Paradise Blown","mbid":"0321d916-5799-4eaf-aabc-70fac210465e","artist":{"name":"9 Lazy 9","mbid":"511481ee-1b97-4333-a161-0492f3e1303c"}}},{"timestamp":{"iso":"2009-07-05T22:08:49","unixtimestamp":1246831729},"track":{"name":"It\u0027s Late","mbid":"17798900-ede3-45d2-9b43-e96545c1e02d","artist":{"name":"9 Lazy 9","mbid":"511481ee-1b97-4333-a161-0492f3e1303c"}},"uncorrectedTrack":{"name":"It\u0027s Late","mbid":"17798900-ede3-45d2-9b43-e96545c1e02d","artist":{"name":"9 Lazy 9","mbid":"511481ee-1b97-4333-a161-0492f3e1303c"}},"album":{"name":"Paradise Blown","mbid":"0321d916-5799-4eaf-aabc-70fac210465e","artist":{"name":"9 Lazy 9","mbid":"511481ee-1b97-4333-a161-0492f3e1303c"}}},{"timestamp":{"iso":"2009-07-05T22:14:22","unixtimestamp":1246832062},"track":{"name":"Gossip / Bad Boy","mbid":"0f40cdd5-1a6d-4754-9de5-6ecd24afd7c6","artist":{"name":"9 Lazy 9","mbid":"511481ee-1b97-4333-a161-0492f3e1303c"}},"uncorrectedTrack":{"name":"Gossip/Bad Boy","artist":{"name":"9 Lazy 9","mbid":"511481ee-1b97-4333-a161-0492f3e1303c"}},"album":{"name":"Paradise Blown","mbid":"0321d916-5799-4eaf-aabc-70fac210465e","artist":{"name":"9 Lazy 9","mbid":"511481ee-1b97-4333-a161-0492f3e1303c"}}},{"timestamp":{"iso":"2009-07-05T22:16:11","unixtimestamp":1246832171},"track":{"name":"Lotto Jisco","mbid":"8a572b16-341b-405e-b9c7-96fda5fa5001","artist":{"name":"9 Lazy 9","mbid":"511481ee-1b97-4333-a161-0492f3e1303c"}},"uncorrectedTrack":{"name":"Lotto Jisco","mbid":"8a572b16-341b-405e-b9c7-96fda5fa5001","artist":{"name":"9 Lazy 9","mbid":"511481ee-1b97-4333-a161-0492f3e1303c"}},"album":{"name":"Paradise Blown","mbid":"0321d916-5799-4eaf-aabc-70fac210465e","artist":{"name":"9 Lazy 9","mbid":"511481ee-1b97-4333-a161-0492f3e1303c"}}},{"timestamp":{"iso":"2009-07-05T22:39:34","unixtimestamp":1246833574},"track":{"name":"The Woodworm","mbid":"215bc2a4-992b-4027-b3a3-5f4c2adb8124","artist":{"name":"9 Lazy 9","mbid":"511481ee-1b97-4333-a161-0492f3e1303c"}},"uncorrectedTrack":{"name":"The Woodworm","mbid":"215bc2a4-992b-4027-b3a3-5f4c2adb8124","artist":{"name":"9 Lazy 9","mbid":"511481ee-1b97-4333-a161-0492f3e1303c"}},"album":{"name":"Sweet Jones","mbid":"53d6e272-42f3-4dbc-b563-d405ed1da6ba","artist":{"name":"9 Lazy 9","mbid":"511481ee-1b97-4333-a161-0492f3e1303c"}}},{"timestamp":{"iso":"2009-07-05T22:44:49","unixtimestamp":1246833889},"track":{"name":"Code 3","mbid":"108d8f30-f150-425d-acbf-c790d9b0ef97","artist":{"name":"9 Lazy 9","mbid":"511481ee-1b97-4333-a161-0492f3e1303c"}},"uncorrectedTrack":{"name":"Code 3","mbid":"108d8f30-f150-425d-acbf-c790d9b0ef97","artist":{"name":"9 Lazy 9","mbid":"511481ee-1b97-4333-a161-0492f3e1303c"}},"album":{"name":"Sweet Jones","mbid":"53d6e272-42f3-4dbc-b563-d405ed1da6ba","artist":{"name":"9 Lazy 9","mbid":"511481ee-1b97-4333-a161-0492f3e1303c"}}},{"timestamp":{"iso":"2009-07-05T22:49:06","unixtimestamp":1246834146},"track":{"name":"Sunday Morning","artist":{"name":"9 Lazy 9","mbid":"511481ee-1b97-4333-a161-0492f3e1303c"}},"uncorrectedTrack":{"name":"Sunday Morning","artist":{"name":"9 Lazy 9","mbid":"511481ee-1b97-4333-a161-0492f3e1303c"}},"album":{"name":"Sweet Jones","mbid":"53d6e272-42f3-4dbc-b563-d405ed1da6ba","artist":{"name":"9 Lazy 9","mbid":"511481ee-1b97-4333-a161-0492f3e1303c"}}},{"timestamp":{"iso":"2009-07-05T22:53:17","unixtimestamp":1246834397},"track":{"name":"Poundstretcher","mbid":"8cc020d8-e239-4901-aea4-9afe48c1c4d2","artist":{"name":"9 Lazy 9","mbid":"511481ee-1b97-4333-a161-0492f3e1303c"}},"uncorrectedTrack":{"name":"Pound Stretcher","artist":{"name":"9 Lazy 9","mbid":"511481ee-1b97-4333-a161-0492f3e1303c"}},"album":{"name":"Sweet Jones","mbid":"53d6e272-42f3-4dbc-b563-d405ed1da6ba","artist":{"name":"9 Lazy 9","mbid":"511481ee-1b97-4333-a161-0492f3e1303c"}}},{"timestamp":{"iso":"2009-07-05T23:00:57","unixtimestamp":1246834857},"track":{"name":"Keep Going Daddy","mbid":"de1ff113-022e-4f71-9489-c9aafe09dda8","artist":{"name":"9 Lazy 9","mbid":"511481ee-1b97-4333-a161-0492f3e1303c"}},"uncorrectedTrack":{"name":"Keep Going Daddy","mbid":"de1ff113-022e-4f71-9489-c9aafe09dda8","artist":{"name":"9 Lazy 9","mbid":"511481ee-1b97-4333-a161-0492f3e1303c"}},"album":{"name":"Sweet Jones","mbid":"53d6e272-42f3-4dbc-b563-d405ed1da6ba","artist":{"name":"9 Lazy 9","mbid":"511481ee-1b97-4333-a161-0492f3e1303c"}}},{"timestamp":{"iso":"2009-07-05T23:05:59","unixtimestamp":1246835159},"track":{"name":"Big Six","mbid":"948aa8f5-0b3b-480c-8bd4-6f6cff872445","artist":{"name":"9 Lazy 9","mbid":"511481ee-1b97-4333-a161-0492f3e1303c"}},"uncorrectedTrack":{"name":"Big Six","mbid":"948aa8f5-0b3b-480c-8bd4-6f6cff872445","artist":{"name":"9 Lazy 9","mbid":"511481ee-1b97-4333-a161-0492f3e1303c"}},"album":{"name":"Sweet Jones","mbid":"53d6e272-42f3-4dbc-b563-d405ed1da6ba","artist":{"name":"9 Lazy 9","mbid":"511481ee-1b97-4333-a161-0492f3e1303c"}}},{"timestamp":{"iso":"2009-07-05T23:10:03","unixtimestamp":1246835403},"track":{"name":"Grazing Maize","mbid":"fd37bea6-5a09-4cf7-95c4-c7dd0d296e3b","artist":{"name":"9 Lazy 9","mbid":"511481ee-1b97-4333-a161-0492f3e1303c"}},"uncorrectedTrack":{"name":"Grazing Maize","mbid":"fd37bea6-5a09-4cf7-95c4-c7dd0d296e3b","artist":{"name":"9 Lazy 9","mbid":"511481ee-1b97-4333-a161-0492f3e1303c"}},"album":{"name":"Sweet Jones","mbid":"53d6e272-42f3-4dbc-b563-d405ed1da6ba","artist":{"name":"9 Lazy 9","mbid":"511481ee-1b97-4333-a161-0492f3e1303c"}}},{"timestamp":{"iso":"2009-07-05T23:11:16","unixtimestamp":1246835476},"track":{"name":"Cosa","mbid":"5145f56c-3612-4432-96ad-fc2bb06ca7fb","artist":{"name":"9 Lazy 9","mbid":"511481ee-1b97-4333-a161-0492f3e1303c"}},"uncorrectedTrack":{"name":"Cosa","mbid":"5145f56c-3612-4432-96ad-fc2bb06ca7fb","artist":{"name":"9 Lazy 9","mbid":"511481ee-1b97-4333-a161-0492f3e1303c"}},"album":{"name":"Sweet Jones","mbid":"53d6e272-42f3-4dbc-b563-d405ed1da6ba","artist":{"name":"9 Lazy 9","mbid":"511481ee-1b97-4333-a161-0492f3e1303c"}}},{"timestamp":{"iso":"2009-07-05T23:17:53","unixtimestamp":1246835873},"track":{"name":"Tumbleweed","mbid":"76a8a8c8-8077-4de1-987e-c5e85b201355","artist":{"name":"9 Lazy 9","mbid":"511481ee-1b97-4333-a161-0492f3e1303c"}},"uncorrectedTrack":{"name":"Tumble Weed","artist":{"name":"9 Lazy 9","mbid":"511481ee-1b97-4333-a161-0492f3e1303c"}},"album":{"name":"Sweet Jones","mbid":"53d6e272-42f3-4dbc-b563-d405ed1da6ba","artist":{"name":"9 Lazy 9","mbid":"511481ee-1b97-4333-a161-0492f3e1303c"}}},{"timestamp":{"iso":"2009-07-05T23:21:06","unixtimestamp":1246836066},"track":{"name":"Carborante","mbid":"f080b4bb-5d80-4bf3-8e82-4b0b8525bcc0","artist":{"name":"9 Lazy 9","mbid":"511481ee-1b97-4333-a161-0492f3e1303c"}},"uncorrectedTrack":{"name":"Carborante","mbid":"f080b4bb-5d80-4bf3-8e82-4b0b8525bcc0","artist":{"name":"9 Lazy 9","mbid":"511481ee-1b97-4333-a161-0492f3e1303c"}},"album":{"name":"Sweet Jones","mbid":"53d6e272-42f3-4dbc-b563-d405ed1da6ba","artist":{"name":"9 Lazy 9","mbid":"511481ee-1b97-4333-a161-0492f3e1303c"}}},{"timestamp":{"iso":"2009-07-05T23:24:29","unixtimestamp":1246836269},"track":{"name":"The Flying Nun","mbid":"6474039d-f40a-41a1-b294-ab51d0aad8ca","artist":{"name":"9 Lazy 9","mbid":"511481ee-1b97-4333-a161-0492f3e1303c"}},"uncorrectedTrack":{"name":"The Flying Nun","mbid":"6474039d-f40a-41a1-b294-ab51d0aad8ca","artist":{"name":"9 Lazy 9","mbid":"511481ee-1b97-4333-a161-0492f3e1303c"}},"album":{"name":"Sweet Jones","mbid":"53d6e272-42f3-4dbc-b563-d405ed1da6ba","artist":{"name":"9 Lazy 9","mbid":"511481ee-1b97-4333-a161-0492f3e1303c"}}},{"timestamp":{"iso":"2009-07-05T23:27:32","unixtimestamp":1246836452},"track":{"name":"The Last of the West","mbid":"11771083-bf43-475d-a451-4a419ab13bf3","artist":{"name":"9 Lazy 9","mbid":"511481ee-1b97-4333-a161-0492f3e1303c"}},"uncorrectedTrack":{"name":"The Last of the West","mbid":"11771083-bf43-475d-a451-4a419ab13bf3","artist":{"name":"9 Lazy 9","mbid":"511481ee-1b97-4333-a161-0492f3e1303c"}},"album":{"name":"Sweet Jones","mbid":"53d6e272-42f3-4dbc-b563-d405ed1da6ba","artist":{"name":"9 Lazy 9","mbid":"511481ee-1b97-4333-a161-0492f3e1303c"}}},{"timestamp":{"iso":"2009-07-06T06:37:51","unixtimestamp":1246862271},"track":{"name":"Elephunk","mbid":"8b15ee06-c250-47c5-81ce-6f8faf50e742","artist":{"name":"Baby Mammoth","mbid":"a74b14a2-28c5-4cfd-95a4-9ebb1c5d1a18"}},"uncorrectedTrack":{"name":"Elephunk","mbid":"8b15ee06-c250-47c5-81ce-6f8faf50e742","artist":{"name":"Baby Mammoth","mbid":"a74b14a2-28c5-4cfd-95a4-9ebb1c5d1a18"}},"album":{"name":"Motion Without Pain","mbid":"a5ce7d87-28f5-4561-8c73-ae310ecfe231","artist":{"name":"Baby Mammoth","mbid":"a74b14a2-28c5-4cfd-95a4-9ebb1c5d1a18"}}},{"timestamp":{"iso":"2009-07-06T06:46:10","unixtimestamp":1246862770},"track":{"name":"Pacific Glitter","mbid":"7dbe2ddf-678e-40d4-9558-c4727a8f442b","artist":{"name":"Baby Mammoth","mbid":"a74b14a2-28c5-4cfd-95a4-9ebb1c5d1a18"}},"uncorrectedTrack":{"name":"Pacific Glitter","mbid":"7dbe2ddf-678e-40d4-9558-c4727a8f442b","artist":{"name":"Baby Mammoth","mbid":"a74b14a2-28c5-4cfd-95a4-9ebb1c5d1a18"}},"album":{"name":"Motion Without Pain","mbid":"a5ce7d87-28f5-4561-8c73-ae310ecfe231","artist":{"name":"Baby Mammoth","mbid":"a74b14a2-28c5-4cfd-95a4-9ebb1c5d1a18"}}},{"timestamp":{"iso":"2009-07-06T06:51:17","unixtimestamp":1246863077},"track":{"name":"Tasty Maloney","mbid":"4aa7f600-2006-42c5-bc8a-e4447005f275","artist":{"name":"Baby Mammoth","mbid":"a74b14a2-28c5-4cfd-95a4-9ebb1c5d1a18"}},"uncorrectedTrack":{"name":"Tasty Maloney","mbid":"4aa7f600-2006-42c5-bc8a-e4447005f275","artist":{"name":"Baby Mammoth","mbid":"a74b14a2-28c5-4cfd-95a4-9ebb1c5d1a18"}},"album":{"name":"Motion Without Pain","mbid":"a5ce7d87-28f5-4561-8c73-ae310ecfe231","artist":{"name":"Baby Mammoth","mbid":"a74b14a2-28c5-4cfd-95a4-9ebb1c5d1a18"}}},{"timestamp":{"iso":"2009-07-06T06:58:36","unixtimestamp":1246863516},"track":{"name":"The Ghost of Henry","mbid":"15dd15f3-c0b9-4fa6-b290-44c0ddf83404","artist":{"name":"Baby Mammoth","mbid":"a74b14a2-28c5-4cfd-95a4-9ebb1c5d1a18"}},"uncorrectedTrack":{"name":"The Ghost of Henry","mbid":"15dd15f3-c0b9-4fa6-b290-44c0ddf83404","artist":{"name":"Baby Mammoth","mbid":"a74b14a2-28c5-4cfd-95a4-9ebb1c5d1a18"}},"album":{"name":"Motion Without Pain","mbid":"a5ce7d87-28f5-4561-8c73-ae310ecfe231","artist":{"name":"Baby Mammoth","mbid":"a74b14a2-28c5-4cfd-95a4-9ebb1c5d1a18"}}},{"timestamp":{"iso":"2009-07-06T07:03:16","unixtimestamp":1246863796},"track":{"name":"One Foot Up My Arse","mbid":"5d8605a0-005d-4b9f-943b-b3cb6bf507ae","artist":{"name":"Baby Mammoth","mbid":"a74b14a2-28c5-4cfd-95a4-9ebb1c5d1a18"}},"uncorrectedTrack":{"name":"One Foot Up My Arse","mbid":"5d8605a0-005d-4b9f-943b-b3cb6bf507ae","artist":{"name":"Baby Mammoth","mbid":"a74b14a2-28c5-4cfd-95a4-9ebb1c5d1a18"}},"album":{"name":"Motion Without Pain","mbid":"a5ce7d87-28f5-4561-8c73-ae310ecfe231","artist":{"name":"Baby Mammoth","mbid":"a74b14a2-28c5-4cfd-95a4-9ebb1c5d1a18"}}},{"timestamp":{"iso":"2009-07-06T07:09:50","unixtimestamp":1246864190},"track":{"name":"Ebb \u0026 Flow","artist":{"name":"Baby Mammoth","mbid":"a74b14a2-28c5-4cfd-95a4-9ebb1c5d1a18"}},"uncorrectedTrack":{"name":"Ebb \u0026 Flow","artist":{"name":"Baby Mammoth","mbid":"a74b14a2-28c5-4cfd-95a4-9ebb1c5d1a18"}},"album":{"name":"Motion Without Pain","mbid":"a5ce7d87-28f5-4561-8c73-ae310ecfe231","artist":{"name":"Baby Mammoth","mbid":"a74b14a2-28c5-4cfd-95a4-9ebb1c5d1a18"}}},{"timestamp":{"iso":"2009-07-06T07:16:01","unixtimestamp":1246864561},"track":{"name":"Pigs in Space","mbid":"096f3b77-48f0-4ae3-bf84-79e451e06578","artist":{"name":"Baby Mammoth","mbid":"a74b14a2-28c5-4cfd-95a4-9ebb1c5d1a18"}},"uncorrectedTrack":{"name":"Pigs in Space","mbid":"096f3b77-48f0-4ae3-bf84-79e451e06578","artist":{"name":"Baby Mammoth","mbid":"a74b14a2-28c5-4cfd-95a4-9ebb1c5d1a18"}},"album":{"name":"Motion Without Pain","mbid":"a5ce7d87-28f5-4561-8c73-ae310ecfe231","artist":{"name":"Baby Mammoth","mbid":"a74b14a2-28c5-4cfd-95a4-9ebb1c5d1a18"}}},{"timestamp":{"iso":"2009-07-06T07:49:18","unixtimestamp":1246866558},"track":{"name":"Frank Furtive","mbid":"d93e2d98-3aa4-463a-88dd-9de60acf8575","artist":{"name":"Baby Mammoth","mbid":"a74b14a2-28c5-4cfd-95a4-9ebb1c5d1a18"}},"uncorrectedTrack":{"name":"Frank Furtive","mbid":"d93e2d98-3aa4-463a-88dd-9de60acf8575","artist":{"name":"Baby Mammoth","mbid":"a74b14a2-28c5-4cfd-95a4-9ebb1c5d1a18"}},"album":{"name":"Another Day at the Orifice","mbid":"b2f1f36c-cece-49f0-aabf-f5307027fb07","artist":{"name":"Baby Mammoth","mbid":"a74b14a2-28c5-4cfd-95a4-9ebb1c5d1a18"}}},{"timestamp":{"iso":"2009-07-06T07:56:14","unixtimestamp":1246866974},"track":{"name":"100% Polyester","mbid":"c2305d4e-aa24-4658-a41c-3991265d6eaf","artist":{"name":"Baby Mammoth","mbid":"a74b14a2-28c5-4cfd-95a4-9ebb1c5d1a18"}},"uncorrectedTrack":{"name":"100% Polyester","mbid":"c2305d4e-aa24-4658-a41c-3991265d6eaf","artist":{"name":"Baby Mammoth","mbid":"a74b14a2-28c5-4cfd-95a4-9ebb1c5d1a18"}},"album":{"name":"Another Day at the Orifice","mbid":"b2f1f36c-cece-49f0-aabf-f5307027fb07","artist":{"name":"Baby Mammoth","mbid":"a74b14a2-28c5-4cfd-95a4-9ebb1c5d1a18"}}},{"timestamp":{"iso":"2009-07-06T08:03:29","unixtimestamp":1246867409},"track":{"name":"Three Wheeler","mbid":"29b8d0e6-d40c-4cdb-8334-099b9a2cafe6","artist":{"name":"Baby Mammoth","mbid":"a74b14a2-28c5-4cfd-95a4-9ebb1c5d1a18"}},"uncorrectedTrack":{"name":"Tree Wheeler","artist":{"name":"Baby Mammoth","mbid":"a74b14a2-28c5-4cfd-95a4-9ebb1c5d1a18"}},"album":{"name":"Another Day at the Orifice","mbid":"b2f1f36c-cece-49f0-aabf-f5307027fb07","artist":{"name":"Baby Mammoth","mbid":"a74b14a2-28c5-4cfd-95a4-9ebb1c5d1a18"}}},{"timestamp":{"iso":"2009-07-06T08:07:35","unixtimestamp":1246867655},"track":{"name":"Thighwig","mbid":"1b508e70-aad1-450f-86cd-da8c256b08ee","artist":{"name":"Baby Mammoth","mbid":"a74b14a2-28c5-4cfd-95a4-9ebb1c5d1a18"}},"uncorrectedTrack":{"name":"Thighwig","mbid":"1b508e70-aad1-450f-86cd-da8c256b08ee","artist":{"name":"Baby Mammoth","mbid":"a74b14a2-28c5-4cfd-95a4-9ebb1c5d1a18"}},"album":{"name":"Another Day at the Orifice","mbid":"b2f1f36c-cece-49f0-aabf-f5307027fb07","artist":{"name":"Baby Mammoth","mbid":"a74b14a2-28c5-4cfd-95a4-9ebb1c5d1a18"}}},{"timestamp":{"iso":"2009-07-06T08:12:08","unixtimestamp":1246867928},"track":{"name":"Hair Breaks","mbid":"b4570bd6-e3cc-4d47-a46c-4851c018a803","artist":{"name":"Baby Mammoth","mbid":"a74b14a2-28c5-4cfd-95a4-9ebb1c5d1a18"}},"uncorrectedTrack":{"name":"Hair Breaks","mbid":"b4570bd6-e3cc-4d47-a46c-4851c018a803","artist":{"name":"Baby Mammoth","mbid":"a74b14a2-28c5-4cfd-95a4-9ebb1c5d1a18"}},"album":{"name":"Another Day at the Orifice","mbid":"b2f1f36c-cece-49f0-aabf-f5307027fb07","artist":{"name":"Baby Mammoth","mbid":"a74b14a2-28c5-4cfd-95a4-9ebb1c5d1a18"}}},{"timestamp":{"iso":"2009-07-06T08:42:09","unixtimestamp":1246869729},"track":{"name":"Come Again","mbid":"37e29423-293d-4454-b7b6-56ff585d07c9","artist":{"name":"Baby Mammoth","mbid":"a74b14a2-28c5-4cfd-95a4-9ebb1c5d1a18"}},"uncorrectedTrack":{"name":"Come Again","mbid":"37e29423-293d-4454-b7b6-56ff585d07c9","artist":{"name":"Baby Mammoth","mbid":"a74b14a2-28c5-4cfd-95a4-9ebb1c5d1a18"}},"album":{"name":"10,000 Years Beneath The Street","mbid":"6c5e1313-e615-4c81-aec4-324a17213211","artist":{"name":"Baby Mammoth","mbid":"a74b14a2-28c5-4cfd-95a4-9ebb1c5d1a18"}}},{"timestamp":{"iso":"2009-07-06T08:49:19","unixtimestamp":1246870159},"track":{"name":"Mysterious Muses","mbid":"437334cf-a036-46af-8028-817980572110","artist":{"name":"Baby Mammoth","mbid":"a74b14a2-28c5-4cfd-95a4-9ebb1c5d1a18"}},"uncorrectedTrack":{"name":"Mysterious Muses","mbid":"437334cf-a036-46af-8028-817980572110","artist":{"name":"Baby Mammoth","mbid":"a74b14a2-28c5-4cfd-95a4-9ebb1c5d1a18"}},"album":{"name":"10,000 Years Beneath The Street","mbid":"6c5e1313-e615-4c81-aec4-324a17213211","artist":{"name":"Baby Mammoth","mbid":"a74b14a2-28c5-4cfd-95a4-9ebb1c5d1a18"}}},{"timestamp":{"iso":"2009-07-06T08:55:32","unixtimestamp":1246870532},"track":{"name":"Whiskey Soul","mbid":"8f18064d-2c48-447b-9dcb-5e9b2d5164d7","artist":{"name":"Baby Mammoth","mbid":"a74b14a2-28c5-4cfd-95a4-9ebb1c5d1a18"}},"uncorrectedTrack":{"name":"Whiskey Soul","mbid":"8f18064d-2c48-447b-9dcb-5e9b2d5164d7","artist":{"name":"Baby Mammoth","mbid":"a74b14a2-28c5-4cfd-95a4-9ebb1c5d1a18"}},"album":{"name":"10,000 Years Beneath The Street","mbid":"6c5e1313-e615-4c81-aec4-324a17213211","artist":{"name":"Baby Mammoth","mbid":"a74b14a2-28c5-4cfd-95a4-9ebb1c5d1a18"}}},{"timestamp":{"iso":"2009-07-06T09:00:46","unixtimestamp":1246870846},"track":{"name":"Dima","mbid":"2ca748f6-463d-4490-8236-4fefa3ad0c5e","artist":{"name":"Baby Mammoth","mbid":"a74b14a2-28c5-4cfd-95a4-9ebb1c5d1a18"}},"uncorrectedTrack":{"name":"Dima","mbid":"2ca748f6-463d-4490-8236-4fefa3ad0c5e","artist":{"name":"Baby Mammoth","mbid":"a74b14a2-28c5-4cfd-95a4-9ebb1c5d1a18"}},"album":{"name":"10,000 Years Beneath The Street","mbid":"6c5e1313-e615-4c81-aec4-324a17213211","artist":{"name":"Baby Mammoth","mbid":"a74b14a2-28c5-4cfd-95a4-9ebb1c5d1a18"}}},{"timestamp":{"iso":"2009-07-06T09:06:38","unixtimestamp":1246871198},"track":{"name":"Venus Vibe Trap","mbid":"2fbab79e-c750-4a1e-98b3-851748d14cc9","artist":{"name":"Baby Mammoth","mbid":"a74b14a2-28c5-4cfd-95a4-9ebb1c5d1a18"}},"uncorrectedTrack":{"name":"Venus Vibe Trap","mbid":"2fbab79e-c750-4a1e-98b3-851748d14cc9","artist":{"name":"Baby Mammoth","mbid":"a74b14a2-28c5-4cfd-95a4-9ebb1c5d1a18"}},"album":{"name":"10,000 Years Beneath The Street","mbid":"6c5e1313-e615-4c81-aec4-324a17213211","artist":{"name":"Baby Mammoth","mbid":"a74b14a2-28c5-4cfd-95a4-9ebb1c5d1a18"}}},{"timestamp":{"iso":"2009-07-07T23:25:49","unixtimestamp":1247009149},"track":{"name":"miss you","artist":{"name":"Miss You"}},"uncorrectedTrack":{"name":"miss you","artist":{"name":"Miss You"}},"album":{"name":"Paris - The Sex, The City, The Music","artist":{"name":"Miss You"}}},{"timestamp":{"iso":"2009-07-07T23:29:22","unixtimestamp":1247009362},"track":{"name":"Espagnolade","artist":{"name":"Espagnolade"}},"uncorrectedTrack":{"name":"Espagnolade","artist":{"name":"Espagnolade"}},"album":{"name":"Paris - The Sex, The City, The Music","artist":{"name":"Espagnolade"}}},{"timestamp":{"iso":"2009-07-07T23:33:39","unixtimestamp":1247009619},"track":{"name":"san fransisco","artist":{"name":"San Fransisco"}},"uncorrectedTrack":{"name":"san fransisco","artist":{"name":"San Fransisco"}},"album":{"name":"Paris - The Sex, The City, The Music","artist":{"name":"San Fransisco"}}},{"timestamp":{"iso":"2009-07-07T23:40:47","unixtimestamp":1247010047},"track":{"name":"Haitari","artist":{"name":"Haitari"}},"uncorrectedTrack":{"name":"Haitari","artist":{"name":"Haitari"}},"album":{"name":"Paris - The Sex, The City, The Music","artist":{"name":"Haitari"}}},{"timestamp":{"iso":"2009-07-07T23:44:41","unixtimestamp":1247010281},"track":{"name":"Pop Art","artist":{"name":"Pop Art","mbid":"3f857252-f599-44ef-b47e-5cedf2149214"}},"uncorrectedTrack":{"name":"Pop Art","artist":{"name":"Pop Art","mbid":"3f857252-f599-44ef-b47e-5cedf2149214"}},"album":{"name":"Paris - The Sex, The City, The Music","artist":{"name":"Pop Art","mbid":"3f857252-f599-44ef-b47e-5cedf2149214"}}},{"timestamp":{"iso":"2009-07-07T23:48:04","unixtimestamp":1247010484},"track":{"name":"The Date","artist":{"name":"The Date"}},"uncorrectedTrack":{"name":"The Date","artist":{"name":"The Date"}},"album":{"name":"Paris - The Sex, The City, The Music","artist":{"name":"The Date"}}},{"timestamp":{"iso":"2009-07-07T23:52:02","unixtimestamp":1247010722},"track":{"name":"Jungle Man","artist":{"name":"Jungle Man"}},"uncorrectedTrack":{"name":"Jungle Man","artist":{"name":"Jungle Man"}},"album":{"name":"Paris - The Sex, The City, The Music","artist":{"name":"Jungle Man"}}},{"timestamp":{"iso":"2009-07-07T23:56:06","unixtimestamp":1247010966},"track":{"name":"Electronic","artist":{"name":"Electronic","mbid":"3cdb360e-d0a2-459f-92f6-f0f28e62127d"}},"uncorrectedTrack":{"name":"Electronic","artist":{"name":"Electronic","mbid":"3cdb360e-d0a2-459f-92f6-f0f28e62127d"}},"album":{"name":"Paris - The Sex, The City, The Music","artist":{"name":"Electronic","mbid":"3cdb360e-d0a2-459f-92f6-f0f28e62127d"}}},{"timestamp":{"iso":"2009-07-08T00:00:39","unixtimestamp":1247011239},"track":{"name":"Americaine","artist":{"name":"Americaine"}},"uncorrectedTrack":{"name":"Americaine","artist":{"name":"Americaine"}},"album":{"name":"Paris - The Sex, The City, The Music","artist":{"name":"Americaine"}}},{"timestamp":{"iso":"2009-07-08T00:05:00","unixtimestamp":1247011500},"track":{"name":"To Hard Try And Find","artist":{"name":"To Hard Try And Find"}},"uncorrectedTrack":{"name":"To Hard Try And Find","artist":{"name":"To Hard Try And Find"}},"album":{"name":"Paris - The Sex, The City, The Music","artist":{"name":"To Hard Try And Find"}}},{"timestamp":{"iso":"2009-07-08T00:09:00","unixtimestamp":1247011740},"track":{"name":"Forever Shirley","artist":{"name":"Forever Shirley"}},"uncorrectedTrack":{"name":"Forever Shirley","artist":{"name":"Forever Shirley"}},"album":{"name":"Paris - The Sex, The City, The Music","artist":{"name":"Forever Shirley"}}},{"timestamp":{"iso":"2009-07-08T00:12:53","unixtimestamp":1247011973},"track":{"name":"Unplug","artist":{"name":"Unplug"}},"uncorrectedTrack":{"name":"Unplug","artist":{"name":"Unplug"}},"album":{"name":"Paris - The Sex, The City, The Music","artist":{"name":"Unplug"}}},{"timestamp":{"iso":"2009-07-08T00:16:25","unixtimestamp":1247012185},"track":{"name":"Sugar Babe","artist":{"name":"SUGAR BABE"}},"uncorrectedTrack":{"name":"Sugar Babe","artist":{"name":"SUGAR BABE"}},"album":{"name":"Paris - The Sex, The City, T..","artist":{"name":"SUGAR BABE"}}},{"timestamp":{"iso":"2009-07-08T00:20:33","unixtimestamp":1247012433},"track":{"name":"Cache Cache","artist":{"name":"Cache Cache"}},"uncorrectedTrack":{"name":"Cache Cache","artist":{"name":"Cache Cache"}},"album":{"name":"Paris - The Sex, The City, The Music","artist":{"name":"Cache Cache"}}},{"timestamp":{"iso":"2009-07-08T02:10:28","unixtimestamp":1247019028},"track":{"name":"Good Luck","mbid":"6ddd6f5f-3dbc-4309-8162-da08e39ac02b","artist":{"name":"Basement Jaxx","mbid":"28cbf94d-0700-4095-a188-37e373b069a7"}},"uncorrectedTrack":{"name":"Good Luck (Feat Lisa Kekaula)","artist":{"name":"Basement Jaxx","mbid":"28cbf94d-0700-4095-a188-37e373b069a7"}},"album":{"name":"Kish Kash-ADVANCE","artist":{"name":"Basement Jaxx","mbid":"28cbf94d-0700-4095-a188-37e373b069a7"}}},{"timestamp":{"iso":"2009-07-08T02:15:11","unixtimestamp":1247019311},"track":{"name":"Right Heres The Spot (Feat Nde","artist":{"name":"Basement Jaxx","mbid":"28cbf94d-0700-4095-a188-37e373b069a7"}},"uncorrectedTrack":{"name":"Right Heres The Spot (Feat Nde","artist":{"name":"Basement Jaxx","mbid":"28cbf94d-0700-4095-a188-37e373b069a7"}},"album":{"name":"Kish Kash-ADVANCE","artist":{"name":"Basement Jaxx","mbid":"28cbf94d-0700-4095-a188-37e373b069a7"}}},{"timestamp":{"iso":"2009-07-08T02:19:45","unixtimestamp":1247019585},"track":{"name":"Lucky Star (Feat Dizzee Rascal","artist":{"name":"Basement Jaxx","mbid":"28cbf94d-0700-4095-a188-37e373b069a7"}},"uncorrectedTrack":{"name":"Lucky Star (Feat Dizzee Rascal","artist":{"name":"Basement Jaxx","mbid":"28cbf94d-0700-4095-a188-37e373b069a7"}},"album":{"name":"Kish Kash-ADVANCE","artist":{"name":"Basement Jaxx","mbid":"28cbf94d-0700-4095-a188-37e373b069a7"}}},{"timestamp":{"iso":"2009-07-08T02:24:26","unixtimestamp":1247019866},"track":{"name":"Supersonic (Feat Cotlyn Jackso","artist":{"name":"Basement Jaxx","mbid":"28cbf94d-0700-4095-a188-37e373b069a7"}},"uncorrectedTrack":{"name":"Supersonic (Feat Cotlyn Jackso","artist":{"name":"Basement Jaxx","mbid":"28cbf94d-0700-4095-a188-37e373b069a7"}},"album":{"name":"Kish Kash-ADVANCE","artist":{"name":"Basement Jaxx","mbid":"28cbf94d-0700-4095-a188-37e373b069a7"}}},{"timestamp":{"iso":"2009-07-08T02:29:50","unixtimestamp":1247020190},"track":{"name":"Plug It In (Feat JC Chasez)","artist":{"name":"Basement Jaxx","mbid":"28cbf94d-0700-4095-a188-37e373b069a7"}},"uncorrectedTrack":{"name":"Plug It In (Feat JC Chasez)","artist":{"name":"Basement Jaxx","mbid":"28cbf94d-0700-4095-a188-37e373b069a7"}},"album":{"name":"Kish Kash-ADVANCE","artist":{"name":"Basement Jaxx","mbid":"28cbf94d-0700-4095-a188-37e373b069a7"}}},{"timestamp":{"iso":"2009-07-08T02:34:42","unixtimestamp":1247020482},"track":{"name":"Cosmolude","mbid":"46552707-fca7-4133-81cb-e47846bf4f54","artist":{"name":"Basement Jaxx","mbid":"28cbf94d-0700-4095-a188-37e373b069a7"}},"uncorrectedTrack":{"name":"Cosmolude","mbid":"46552707-fca7-4133-81cb-e47846bf4f54","artist":{"name":"Basement Jaxx","mbid":"28cbf94d-0700-4095-a188-37e373b069a7"}},"album":{"name":"Kish Kash-ADVANCE","artist":{"name":"Basement Jaxx","mbid":"28cbf94d-0700-4095-a188-37e373b069a7"}}},{"timestamp":{"iso":"2009-07-08T02:35:36","unixtimestamp":1247020536},"track":{"name":"If I Ever Recover","mbid":"6b56dd85-9182-40cd-ad38-729878183178","artist":{"name":"Basement Jaxx","mbid":"28cbf94d-0700-4095-a188-37e373b069a7"}},"uncorrectedTrack":{"name":"If I Ever Recover","mbid":"6b56dd85-9182-40cd-ad38-729878183178","artist":{"name":"Basement Jaxx","mbid":"28cbf94d-0700-4095-a188-37e373b069a7"}},"album":{"name":"Kish Kash-ADVANCE","artist":{"name":"Basement Jaxx","mbid":"28cbf94d-0700-4095-a188-37e373b069a7"}}},{"timestamp":{"iso":"2009-07-08T02:38:59","unixtimestamp":1247020739},"track":{"name":"Cish Cash (Feat Siouxsie Sioux","artist":{"name":"Basement Jaxx","mbid":"28cbf94d-0700-4095-a188-37e373b069a7"}},"uncorrectedTrack":{"name":"Cish Cash (Feat Siouxsie Sioux","artist":{"name":"Basement Jaxx","mbid":"28cbf94d-0700-4095-a188-37e373b069a7"}},"album":{"name":"Kish Kash-ADVANCE","artist":{"name":"Basement Jaxx","mbid":"28cbf94d-0700-4095-a188-37e373b069a7"}}},{"timestamp":{"iso":"2009-07-08T02:43:18","unixtimestamp":1247020998},"track":{"name":"Tonight (Feat Phoebe)","artist":{"name":"Basement Jaxx","mbid":"28cbf94d-0700-4095-a188-37e373b069a7"}},"uncorrectedTrack":{"name":"Tonight (Feat Phoebe)","artist":{"name":"Basement Jaxx","mbid":"28cbf94d-0700-4095-a188-37e373b069a7"}},"album":{"name":"Kish Kash-ADVANCE","artist":{"name":"Basement Jaxx","mbid":"28cbf94d-0700-4095-a188-37e373b069a7"}}},{"timestamp":{"iso":"2009-07-08T02:47:20","unixtimestamp":1247021240},"track":{"name":"Hot N Cold","artist":{"name":"Basement Jaxx","mbid":"28cbf94d-0700-4095-a188-37e373b069a7"}},"uncorrectedTrack":{"name":"Hot N Cold","artist":{"name":"Basement Jaxx","mbid":"28cbf94d-0700-4095-a188-37e373b069a7"}},"album":{"name":"Kish Kash-ADVANCE","artist":{"name":"Basement Jaxx","mbid":"28cbf94d-0700-4095-a188-37e373b069a7"}}},{"timestamp":{"iso":"2009-07-08T02:51:20","unixtimestamp":1247021480},"track":{"name":"Living Room","mbid":"3f904a0e-f6b4-438d-8fcc-5a6febd236e7","artist":{"name":"Basement Jaxx","mbid":"28cbf94d-0700-4095-a188-37e373b069a7"}},"uncorrectedTrack":{"name":"Living Room","mbid":"3f904a0e-f6b4-438d-8fcc-5a6febd236e7","artist":{"name":"Basement Jaxx","mbid":"28cbf94d-0700-4095-a188-37e373b069a7"}},"album":{"name":"Kish Kash-ADVANCE","artist":{"name":"Basement Jaxx","mbid":"28cbf94d-0700-4095-a188-37e373b069a7"}}},{"timestamp":{"iso":"2009-07-09T08:39:01","unixtimestamp":1247128741},"track":{"name":"Untouchable Face","mbid":"0e1a8128-c5c6-4769-96eb-e30726c4e5c6","artist":{"name":"Ani DiFranco","mbid":"a7bdc71f-697a-45d9-92b2-a01fbbe50272"}},"uncorrectedTrack":{"name":"Untouchable Face","mbid":"0e1a8128-c5c6-4769-96eb-e30726c4e5c6","artist":{"name":"Ani DiFranco","mbid":"a7bdc71f-697a-45d9-92b2-a01fbbe50272"}},"album":{"name":"Living in Clip (disc 2)","artist":{"name":"Ani DiFranco","mbid":"a7bdc71f-697a-45d9-92b2-a01fbbe50272"}}},{"timestamp":{"iso":"2009-07-09T08:42:38","unixtimestamp":1247128958},"track":{"name":"Shameless","mbid":"81841ec4-ae94-4df5-af41-ad1b1a0772e0","artist":{"name":"Ani DiFranco","mbid":"a7bdc71f-697a-45d9-92b2-a01fbbe50272"}},"uncorrectedTrack":{"name":"Shameless","mbid":"81841ec4-ae94-4df5-af41-ad1b1a0772e0","artist":{"name":"Ani DiFranco","mbid":"a7bdc71f-697a-45d9-92b2-a01fbbe50272"}},"album":{"name":"Living in Clip (disc 2)","artist":{"name":"Ani DiFranco","mbid":"a7bdc71f-697a-45d9-92b2-a01fbbe50272"}}},{"timestamp":{"iso":"2009-07-09T08:48:37","unixtimestamp":1247129317},"track":{"name":"Distracted","mbid":"bf928e56-564f-44c2-9a37-990f7ed2893d","artist":{"name":"Ani DiFranco","mbid":"a7bdc71f-697a-45d9-92b2-a01fbbe50272"}},"uncorrectedTrack":{"name":"Distracted","mbid":"bf928e56-564f-44c2-9a37-990f7ed2893d","artist":{"name":"Ani DiFranco","mbid":"a7bdc71f-697a-45d9-92b2-a01fbbe50272"}},"album":{"name":"Living in Clip (disc 2)","artist":{"name":"Ani DiFranco","mbid":"a7bdc71f-697a-45d9-92b2-a01fbbe50272"}}},{"timestamp":{"iso":"2009-07-09T08:49:46","unixtimestamp":1247129386},"track":{"name":"Adam and Eve","mbid":"46bba4b8-c583-425e-8a52-762d19ffc52c","artist":{"name":"Ani DiFranco","mbid":"a7bdc71f-697a-45d9-92b2-a01fbbe50272"}},"uncorrectedTrack":{"name":"Adam and Eve","mbid":"46bba4b8-c583-425e-8a52-762d19ffc52c","artist":{"name":"Ani DiFranco","mbid":"a7bdc71f-697a-45d9-92b2-a01fbbe50272"}},"album":{"name":"Living in Clip (disc 2)","artist":{"name":"Ani DiFranco","mbid":"a7bdc71f-697a-45d9-92b2-a01fbbe50272"}}},{"timestamp":{"iso":"2009-07-09T08:55:22","unixtimestamp":1247129722},"track":{"name":"Fire Door","mbid":"54fd7a53-1821-46aa-9b31-aa168ff82848","artist":{"name":"Ani DiFranco","mbid":"a7bdc71f-697a-45d9-92b2-a01fbbe50272"}},"uncorrectedTrack":{"name":"Fire Door","mbid":"54fd7a53-1821-46aa-9b31-aa168ff82848","artist":{"name":"Ani DiFranco","mbid":"a7bdc71f-697a-45d9-92b2-a01fbbe50272"}},"album":{"name":"Living in Clip (disc 2)","artist":{"name":"Ani DiFranco","mbid":"a7bdc71f-697a-45d9-92b2-a01fbbe50272"}}},{"timestamp":{"iso":"2009-07-09T08:59:25","unixtimestamp":1247129965},"track":{"name":"Both Hands","mbid":"0a3eb973-8376-4385-8267-aa083b8ecc6e","artist":{"name":"Ani DiFranco","mbid":"a7bdc71f-697a-45d9-92b2-a01fbbe50272"}},"uncorrectedTrack":{"name":"Both Hands","mbid":"0a3eb973-8376-4385-8267-aa083b8ecc6e","artist":{"name":"Ani DiFranco","mbid":"a7bdc71f-697a-45d9-92b2-a01fbbe50272"}},"album":{"name":"Living in Clip (disc 2)","artist":{"name":"Ani DiFranco","mbid":"a7bdc71f-697a-45d9-92b2-a01fbbe50272"}}},{"timestamp":{"iso":"2009-07-09T09:04:18","unixtimestamp":1247130258},"track":{"name":"Out Of Habit","mbid":"99b2b4e3-bb6f-4289-87bc-5c1ccd6cd012","artist":{"name":"Ani DiFranco","mbid":"a7bdc71f-697a-45d9-92b2-a01fbbe50272"}},"uncorrectedTrack":{"name":"Out Of Habit","mbid":"99b2b4e3-bb6f-4289-87bc-5c1ccd6cd012","artist":{"name":"Ani DiFranco","mbid":"a7bdc71f-697a-45d9-92b2-a01fbbe50272"}},"album":{"name":"Living in Clip (disc 2)","artist":{"name":"Ani DiFranco","mbid":"a7bdc71f-697a-45d9-92b2-a01fbbe50272"}}},{"timestamp":{"iso":"2009-07-09T09:07:58","unixtimestamp":1247130478},"track":{"name":"Every State Line","mbid":"535c9b01-17f8-48b1-b4d5-0b4c77462aa6","artist":{"name":"Ani DiFranco","mbid":"a7bdc71f-697a-45d9-92b2-a01fbbe50272"}},"uncorrectedTrack":{"name":"Every State Line","mbid":"535c9b01-17f8-48b1-b4d5-0b4c77462aa6","artist":{"name":"Ani DiFranco","mbid":"a7bdc71f-697a-45d9-92b2-a01fbbe50272"}},"album":{"name":"Living in Clip (disc 2)","artist":{"name":"Ani DiFranco","mbid":"a7bdc71f-697a-45d9-92b2-a01fbbe50272"}}},{"timestamp":{"iso":"2009-07-09T09:11:54","unixtimestamp":1247130714},"track":{"name":"Not So Soft","mbid":"c6e6e022-db02-40a5-abc9-2ac9e261083d","artist":{"name":"Ani DiFranco","mbid":"a7bdc71f-697a-45d9-92b2-a01fbbe50272"}},"uncorrectedTrack":{"name":"Not So Soft","mbid":"c6e6e022-db02-40a5-abc9-2ac9e261083d","artist":{"name":"Ani DiFranco","mbid":"a7bdc71f-697a-45d9-92b2-a01fbbe50272"}},"album":{"name":"Living in Clip (disc 2)","artist":{"name":"Ani DiFranco","mbid":"a7bdc71f-697a-45d9-92b2-a01fbbe50272"}}},{"timestamp":{"iso":"2009-07-09T09:15:54","unixtimestamp":1247130954},"track":{"name":"Travel Tips","mbid":"24c34ec0-df35-4823-9aa0-73972cb2809c","artist":{"name":"Ani DiFranco","mbid":"a7bdc71f-697a-45d9-92b2-a01fbbe50272"}},"uncorrectedTrack":{"name":"Travel Tips","mbid":"24c34ec0-df35-4823-9aa0-73972cb2809c","artist":{"name":"Ani DiFranco","mbid":"a7bdc71f-697a-45d9-92b2-a01fbbe50272"}},"album":{"name":"Living in Clip (disc 2)","artist":{"name":"Ani DiFranco","mbid":"a7bdc71f-697a-45d9-92b2-a01fbbe50272"}}},{"timestamp":{"iso":"2009-07-09T09:17:00","unixtimestamp":1247131020},"track":{"name":"Wrong With Me","mbid":"65c37c5d-532e-4e37-9848-51b8dc859470","artist":{"name":"Ani DiFranco","mbid":"a7bdc71f-697a-45d9-92b2-a01fbbe50272"}},"uncorrectedTrack":{"name":"Wrong With Me","mbid":"65c37c5d-532e-4e37-9848-51b8dc859470","artist":{"name":"Ani DiFranco","mbid":"a7bdc71f-697a-45d9-92b2-a01fbbe50272"}},"album":{"name":"Living in Clip (disc 2)","artist":{"name":"Ani DiFranco","mbid":"a7bdc71f-697a-45d9-92b2-a01fbbe50272"}}},{"timestamp":{"iso":"2009-07-09T09:18:58","unixtimestamp":1247131138},"track":{"name":"In Or Out","mbid":"23d12943-d4a5-4732-9622-ced07d931e17","artist":{"name":"Ani DiFranco","mbid":"a7bdc71f-697a-45d9-92b2-a01fbbe50272"}},"uncorrectedTrack":{"name":"In Or Out","mbid":"23d12943-d4a5-4732-9622-ced07d931e17","artist":{"name":"Ani DiFranco","mbid":"a7bdc71f-697a-45d9-92b2-a01fbbe50272"}},"album":{"name":"Living in Clip (disc 2)","artist":{"name":"Ani DiFranco","mbid":"a7bdc71f-697a-45d9-92b2-a01fbbe50272"}}},{"timestamp":{"iso":"2009-07-09T09:22:21","unixtimestamp":1247131341},"track":{"name":"We\u0027re All Gonna Blow","mbid":"ecac1e36-bb9d-4588-832a-b3f955ff848a","artist":{"name":"Ani DiFranco","mbid":"a7bdc71f-697a-45d9-92b2-a01fbbe50272"}},"uncorrectedTrack":{"name":"We\u0027re All Gonna Blow","mbid":"ecac1e36-bb9d-4588-832a-b3f955ff848a","artist":{"name":"Ani DiFranco","mbid":"a7bdc71f-697a-45d9-92b2-a01fbbe50272"}},"album":{"name":"Living in Clip (disc 2)","artist":{"name":"Ani DiFranco","mbid":"a7bdc71f-697a-45d9-92b2-a01fbbe50272"}}},{"timestamp":{"iso":"2009-07-09T09:25:03","unixtimestamp":1247131503},"track":{"name":"Letter To A John","mbid":"bae35e57-6c73-4bb8-a0b0-578f833a64ff","artist":{"name":"Ani DiFranco","mbid":"a7bdc71f-697a-45d9-92b2-a01fbbe50272"}},"uncorrectedTrack":{"name":"Letter To A John","mbid":"bae35e57-6c73-4bb8-a0b0-578f833a64ff","artist":{"name":"Ani DiFranco","mbid":"a7bdc71f-697a-45d9-92b2-a01fbbe50272"}},"album":{"name":"Living in Clip (disc 2)","artist":{"name":"Ani DiFranco","mbid":"a7bdc71f-697a-45d9-92b2-a01fbbe50272"}}},{"timestamp":{"iso":"2009-07-09T09:29:01","unixtimestamp":1247131741},"track":{"name":"Overlap","mbid":"05c85cf1-477d-48e7-adf6-bd9c461a0af1","artist":{"name":"Ani DiFranco","mbid":"a7bdc71f-697a-45d9-92b2-a01fbbe50272"}},"uncorrectedTrack":{"name":"Overlap","mbid":"05c85cf1-477d-48e7-adf6-bd9c461a0af1","artist":{"name":"Ani DiFranco","mbid":"a7bdc71f-697a-45d9-92b2-a01fbbe50272"}},"album":{"name":"Living in Clip (disc 2)","artist":{"name":"Ani DiFranco","mbid":"a7bdc71f-697a-45d9-92b2-a01fbbe50272"}}},{"timestamp":{"iso":"2009-07-09T09:39:12","unixtimestamp":1247132352},"track":{"name":"Future Boy","mbid":"2a0449a6-8d49-4366-addc-50859ce7f0d8","artist":{"name":"Turin Brakes","mbid":"2ecbd923-9daf-4f18-9250-e482ccec4c28"}},"uncorrectedTrack":{"name":"Future Boy","artist":{"name":"Turin Breaks"}},"album":{"name":"Acoustic Chill (disc 2)","artist":{"name":"Turin Breaks"}}},{"timestamp":{"iso":"2009-07-09T09:43:10","unixtimestamp":1247132590},"track":{"name":"Before You Broke My Heart","mbid":"07279638-9cea-4ad0-8c3d-5419fd6b9ee0","artist":{"name":"Chris Coco","mbid":"c41541e9-2284-4a14-b977-3e4d174e2169"}},"uncorrectedTrack":{"name":"Before You Broke My Heart","mbid":"07279638-9cea-4ad0-8c3d-5419fd6b9ee0","artist":{"name":"Chris Coco","mbid":"c41541e9-2284-4a14-b977-3e4d174e2169"}},"album":{"name":"Acoustic Chill (disc 2)","artist":{"name":"Various Artists","mbid":"023671ff-b1ad-4133-a4f3-aadaaadfd2e0"}}},{"timestamp":{"iso":"2009-07-09T09:47:18","unixtimestamp":1247132838},"track":{"name":"Sparks","mbid":"1c3d55b6-41ed-4595-a35f-052771b741f5","artist":{"name":"Röyksopp","mbid":"1c70a3fc-fa3c-4be1-8b55-c3192db8a884"}},"uncorrectedTrack":{"name":"Sparks","artist":{"name":"royksopp"}},"album":{"name":"Acoustic Chill (disc 2)","artist":{"name":"royksopp"}}},{"timestamp":{"iso":"2009-07-09T09:52:44","unixtimestamp":1247133164},"track":{"name":"August Day Song","mbid":"1015ee81-7b7c-4fc8-84ab-8c001a7271be","artist":{"name":"Bebel Gilberto","mbid":"8777a849-fb4e-4430-9918-170f619c5286"}},"uncorrectedTrack":{"name":"August Day Song","mbid":"1015ee81-7b7c-4fc8-84ab-8c001a7271be","artist":{"name":"Bebel Gilberto","mbid":"8777a849-fb4e-4430-9918-170f619c5286"}},"album":{"name":"Tanto Tempo","mbid":"27b97cd4-5ab6-3a6f-a1f1-edbc6248e5c9","artist":{"name":"Bebel Gilberto","mbid":"8777a849-fb4e-4430-9918-170f619c5286"}}},{"timestamp":{"iso":"2009-07-09T09:57:22","unixtimestamp":1247133442},"track":{"name":"Come a Day","mbid":"41026307-b85a-48da-b48a-8e03d656476c","artist":{"name":"Beth Hirsch","mbid":"e3b3de77-0e3f-4c51-b4f5-b99d6df42c66"}},"uncorrectedTrack":{"name":"Come a Day","mbid":"41026307-b85a-48da-b48a-8e03d656476c","artist":{"name":"Beth Hirsch","mbid":"e3b3de77-0e3f-4c51-b4f5-b99d6df42c66"}},"album":{"name":"Early Days","mbid":"12976ff3-c78d-3e63-a7a1-7e376cbc5f45","artist":{"name":"Beth Hirsch","mbid":"e3b3de77-0e3f-4c51-b4f5-b99d6df42c66"}}},{"timestamp":{"iso":"2009-07-09T10:00:56","unixtimestamp":1247133656},"track":{"name":"Lydia","mbid":"0846ffd6-80b0-4557-9ba9-b1494fc3b833","artist":{"name":"Kathryn Williams","mbid":"e479c9f2-730c-4044-b554-e967320d57e9"}},"uncorrectedTrack":{"name":"Lydia","mbid":"0846ffd6-80b0-4557-9ba9-b1494fc3b833","artist":{"name":"Kathryn Williams","mbid":"e479c9f2-730c-4044-b554-e967320d57e9"}},"album":{"name":"Dog Leap Stairs","mbid":"36811f81-b2b5-48c1-b69e-bffbe52daa15","artist":{"name":"Kathryn Williams","mbid":"e479c9f2-730c-4044-b554-e967320d57e9"}}},{"timestamp":{"iso":"2009-07-09T10:03:42","unixtimestamp":1247133822},"track":{"name":"Maid of the Loch","mbid":"55acfc06-94a2-4ba7-a950-b06774e640df","artist":{"name":"Future Pilot Aka","mbid":"1cece2d1-7d0f-4124-9a87-f5ffc8c77ac6"}},"uncorrectedTrack":{"name":"Maid of the Loch","mbid":"55acfc06-94a2-4ba7-a950-b06774e640df","artist":{"name":"Future Pilot Aka","mbid":"1cece2d1-7d0f-4124-9a87-f5ffc8c77ac6"}},"album":{"name":"Tiny Waves, Mighty Sea","mbid":"456a64df-f772-4a80-97ab-ac3a2faf7b52","artist":{"name":"Future Pilot Aka","mbid":"1cece2d1-7d0f-4124-9a87-f5ffc8c77ac6"}}},{"timestamp":{"iso":"2009-07-09T10:06:46","unixtimestamp":1247134006},"track":{"name":"Arun","mbid":"abe9a841-1742-4666-b360-cf00d6be06b3","artist":{"name":"The Kingsbury Manx","mbid":"23833fa0-f266-44e5-8934-49bf4abcddc4"}},"uncorrectedTrack":{"name":"Arun","mbid":"abe9a841-1742-4666-b360-cf00d6be06b3","artist":{"name":"The Kingsbury Manx","mbid":"23833fa0-f266-44e5-8934-49bf4abcddc4"}},"album":{"name":"Let You Down","mbid":"6ec4ab06-02db-45fe-8f9c-b0a3cbf803ab","artist":{"name":"The Kingsbury Manx","mbid":"23833fa0-f266-44e5-8934-49bf4abcddc4"}}},{"timestamp":{"iso":"2009-07-09T10:10:17","unixtimestamp":1247134217},"track":{"name":"Reprise","mbid":"9d66f99c-0bf3-48dd-9759-c86649141135","artist":{"name":"blueflame","mbid":"4fac8f77-90d2-4cd9-a438-f16bee884870"}},"uncorrectedTrack":{"name":"Reprise","mbid":"9d66f99c-0bf3-48dd-9759-c86649141135","artist":{"name":"blueflame","mbid":"4fac8f77-90d2-4cd9-a438-f16bee884870"}},"album":{"name":"Acoustic Chill (disc 2)","artist":{"name":"Various Artists","mbid":"023671ff-b1ad-4133-a4f3-aadaaadfd2e0"}}},{"timestamp":{"iso":"2009-07-09T10:14:17","unixtimestamp":1247134457},"track":{"name":"Moonlight","mbid":"ca19dd71-51a3-448e-b8f3-c840162fcb99","artist":{"name":"Handkandy","mbid":"fa690b16-f959-488e-a418-13636b1479c0"}},"uncorrectedTrack":{"name":"Moonlight","mbid":"ca19dd71-51a3-448e-b8f3-c840162fcb99","artist":{"name":"Handkandy","mbid":"fa690b16-f959-488e-a418-13636b1479c0"}},"album":{"name":"Acoustic Chill (disc 2)","artist":{"name":"Various Artists","mbid":"023671ff-b1ad-4133-a4f3-aadaaadfd2e0"}}},{"timestamp":{"iso":"2009-07-09T10:19:09","unixtimestamp":1247134749},"track":{"name":"Private Sunshine","mbid":"65f4d277-8e47-4cac-bbb5-6388f18e8852","artist":{"name":"Ashley Slater","mbid":"1658c51b-3b8f-4c72-8314-3dd4fa524837"}},"uncorrectedTrack":{"name":"Private Sunshine","mbid":"65f4d277-8e47-4cac-bbb5-6388f18e8852","artist":{"name":"Ashley Slater","mbid":"1658c51b-3b8f-4c72-8314-3dd4fa524837"}},"album":{"name":"Biglounge","mbid":"72ca5bff-5813-4a29-8115-c570a639291e","artist":{"name":"Ashley Slater","mbid":"1658c51b-3b8f-4c72-8314-3dd4fa524837"}}},{"timestamp":{"iso":"2009-07-09T10:23:06","unixtimestamp":1247134986},"track":{"name":"New Home","mbid":"32755109-c9e8-40ed-b7df-875f6535041f","artist":{"name":"Zimpala","mbid":"6be231bd-6552-4316-aef3-a68b0acff5a1"}},"uncorrectedTrack":{"name":"New Home","mbid":"32755109-c9e8-40ed-b7df-875f6535041f","artist":{"name":"Zimpala","mbid":"6be231bd-6552-4316-aef3-a68b0acff5a1"}},"album":{"name":"Almaviva","mbid":"4445240e-7b66-49eb-b8c9-12082a8d9c64","artist":{"name":"Zimpala","mbid":"6be231bd-6552-4316-aef3-a68b0acff5a1"}}},{"timestamp":{"iso":"2009-07-09T10:28:40","unixtimestamp":1247135320},"track":{"name":"Cerulean","mbid":"1084cf03-cfd8-4c65-b672-0882e7c68b89","artist":{"name":"Jon Hopkins","mbid":"0b0c25f4-f31c-46a5-a4fb-ccbf53d663bd"}},"uncorrectedTrack":{"name":"Cerulean","mbid":"1084cf03-cfd8-4c65-b672-0882e7c68b89","artist":{"name":"Jon Hopkins","mbid":"0b0c25f4-f31c-46a5-a4fb-ccbf53d663bd"}},"album":{"name":"Opalescent","mbid":"52866029-e8eb-4cc1-9393-a1e495274480","artist":{"name":"Jon Hopkins","mbid":"0b0c25f4-f31c-46a5-a4fb-ccbf53d663bd"}}},{"timestamp":{"iso":"2009-07-09T10:32:36","unixtimestamp":1247135556},"track":{"name":"Freedub","mbid":"594b8b52-5743-44c1-a104-c5f2016e40c2","artist":{"name":"Blueprint","mbid":"28585fb5-0f84-429b-9caa-a30f97b26977"}},"uncorrectedTrack":{"name":"Freedub","mbid":"594b8b52-5743-44c1-a104-c5f2016e40c2","artist":{"name":"Blueprint","mbid":"28585fb5-0f84-429b-9caa-a30f97b26977"}},"album":{"name":"Acoustic Chill (disc 2)","artist":{"name":"Various Artists","mbid":"023671ff-b1ad-4133-a4f3-aadaaadfd2e0"}}},{"timestamp":{"iso":"2009-07-09T10:41:20","unixtimestamp":1247136080},"track":{"name":"Ehad","artist":{"name":"Zohar","mbid":"53a28080-e154-493e-9b46-7dc024538d21"}},"uncorrectedTrack":{"name":"Ehad","artist":{"name":"Zohar","mbid":"53a28080-e154-493e-9b46-7dc024538d21"}},"album":{"name":"Acoustic Chill (disc 2)","artist":{"name":"Various Artists","mbid":"023671ff-b1ad-4133-a4f3-aadaaadfd2e0"}}},{"timestamp":{"iso":"2009-07-09T10:56:13","unixtimestamp":1247136973},"track":{"name":"Little Plastic Castle","mbid":"1d8bb3c8-e111-4ad8-ae1f-30b61a1e041d","artist":{"name":"Ani DiFranco","mbid":"a7bdc71f-697a-45d9-92b2-a01fbbe50272"}},"uncorrectedTrack":{"name":"Little Plastic Castles","artist":{"name":"Ani DiFranco","mbid":"a7bdc71f-697a-45d9-92b2-a01fbbe50272"}},"album":{"name":"Little Plastic Castles","artist":{"name":"Ani DiFranco","mbid":"a7bdc71f-697a-45d9-92b2-a01fbbe50272"}}},{"timestamp":{"iso":"2009-07-09T11:00:17","unixtimestamp":1247137217},"track":{"name":"Fuel","mbid":"2398d33a-a094-4dd6-8d84-efc4177aaf4e","artist":{"name":"Ani DiFranco","mbid":"a7bdc71f-697a-45d9-92b2-a01fbbe50272"}},"uncorrectedTrack":{"name":"Fuel","mbid":"2398d33a-a094-4dd6-8d84-efc4177aaf4e","artist":{"name":"Ani DiFranco","mbid":"a7bdc71f-697a-45d9-92b2-a01fbbe50272"}},"album":{"name":"Little Plastic Castles","artist":{"name":"Ani DiFranco","mbid":"a7bdc71f-697a-45d9-92b2-a01fbbe50272"}}},{"timestamp":{"iso":"2009-07-09T11:04:18","unixtimestamp":1247137458},"track":{"name":"Gravel","mbid":"cdcafbab-771d-4b7d-84ab-f800cb94ca9f","artist":{"name":"Ani DiFranco","mbid":"a7bdc71f-697a-45d9-92b2-a01fbbe50272"}},"uncorrectedTrack":{"name":"Gravel","mbid":"cdcafbab-771d-4b7d-84ab-f800cb94ca9f","artist":{"name":"Ani DiFranco","mbid":"a7bdc71f-697a-45d9-92b2-a01fbbe50272"}},"album":{"name":"Little Plastic Castles","artist":{"name":"Ani DiFranco","mbid":"a7bdc71f-697a-45d9-92b2-a01fbbe50272"}}},{"timestamp":{"iso":"2009-07-09T11:07:50","unixtimestamp":1247137670},"track":{"name":"As Is","mbid":"ab85ae33-74cc-4e39-998c-e9e6796f78e0","artist":{"name":"Ani DiFranco","mbid":"a7bdc71f-697a-45d9-92b2-a01fbbe50272"}},"uncorrectedTrack":{"name":"As Is","mbid":"ab85ae33-74cc-4e39-998c-e9e6796f78e0","artist":{"name":"Ani DiFranco","mbid":"a7bdc71f-697a-45d9-92b2-a01fbbe50272"}},"album":{"name":"Little Plastic Castles","artist":{"name":"Ani DiFranco","mbid":"a7bdc71f-697a-45d9-92b2-a01fbbe50272"}}},{"timestamp":{"iso":"2009-07-09T11:11:56","unixtimestamp":1247137916},"track":{"name":"Two Little Girls","mbid":"64524acb-fc73-47e4-adc2-d9748a6931e4","artist":{"name":"Ani DiFranco","mbid":"a7bdc71f-697a-45d9-92b2-a01fbbe50272"}},"uncorrectedTrack":{"name":"Two Little Girls","mbid":"64524acb-fc73-47e4-adc2-d9748a6931e4","artist":{"name":"Ani DiFranco","mbid":"a7bdc71f-697a-45d9-92b2-a01fbbe50272"}},"album":{"name":"Little Plastic Castles","artist":{"name":"Ani DiFranco","mbid":"a7bdc71f-697a-45d9-92b2-a01fbbe50272"}}},{"timestamp":{"iso":"2009-07-09T11:16:54","unixtimestamp":1247138214},"track":{"name":"Deep Dish","mbid":"b663d61e-f15a-4969-887e-3e2168a89d74","artist":{"name":"Ani DiFranco","mbid":"a7bdc71f-697a-45d9-92b2-a01fbbe50272"}},"uncorrectedTrack":{"name":"Deep Dish","mbid":"b663d61e-f15a-4969-887e-3e2168a89d74","artist":{"name":"Ani DiFranco","mbid":"a7bdc71f-697a-45d9-92b2-a01fbbe50272"}},"album":{"name":"Little Plastic Castles","artist":{"name":"Ani DiFranco","mbid":"a7bdc71f-697a-45d9-92b2-a01fbbe50272"}}},{"timestamp":{"iso":"2009-07-12T03:21:08","unixtimestamp":1247368868},"track":{"name":"Track You Down","mbid":"37298607-151a-428f-80f9-6015614b6e98","artist":{"name":"Sondre Lerche","mbid":"a1c29c2f-778f-4b02-9ac7-80f0c37cdea9"}},"uncorrectedTrack":{"name":"Track You Down","mbid":"37298607-151a-428f-80f9-6015614b6e98","artist":{"name":"Sondre Lerche","mbid":"a1c29c2f-778f-4b02-9ac7-80f0c37cdea9"}},"album":{"name":"Two Way Monologue","mbid":"e84c0d6b-e4ff-478e-b922-f81226d72228","artist":{"name":"Sondre Lerche","mbid":"a1c29c2f-778f-4b02-9ac7-80f0c37cdea9"}}},{"timestamp":{"iso":"2009-07-12T03:26:34","unixtimestamp":1247369194},"track":{"name":"Figures","mbid":"79544e48-a1e7-4c1a-952a-fe7a56961ea1","artist":{"name":"The Whitest Boy Alive","mbid":"f83781c8-64f9-4657-85bd-51f74d195cfd"}},"uncorrectedTrack":{"name":"Figures","mbid":"79544e48-a1e7-4c1a-952a-fe7a56961ea1","artist":{"name":"The Whitest Boy Alive","mbid":"f83781c8-64f9-4657-85bd-51f74d195cfd"}},"album":{"name":"Dreams","mbid":"b92cdc4d-84e7-3673-87d2-c833966515e7","artist":{"name":"The Whitest Boy Alive","mbid":"f83781c8-64f9-4657-85bd-51f74d195cfd"}}},{"timestamp":{"iso":"2009-07-12T03:30:42","unixtimestamp":1247369442},"track":{"name":"A Short Goodbye","mbid":"1ed8e40a-a365-4a17-adde-45dbd3f6e519","artist":{"name":"Oren Lavie","mbid":"411f15e4-fdad-4d09-beca-0201c2e56727"}},"uncorrectedTrack":{"name":"A Short Goodbye","mbid":"1ed8e40a-a365-4a17-adde-45dbd3f6e519","artist":{"name":"Oren Lavie","mbid":"411f15e4-fdad-4d09-beca-0201c2e56727"}}},{"timestamp":{"iso":"2009-07-12T03:34:15","unixtimestamp":1247369655},"track":{"name":"Heartbeats","mbid":"edfb19c0-8796-46ca-9bb6-cf5314e14419","artist":{"name":"José González","mbid":"cd8c5019-5d75-4d5c-bc28-e1e26a7dd5c8"}},"uncorrectedTrack":{"name":"Heartbeats","mbid":"edfb19c0-8796-46ca-9bb6-cf5314e14419","artist":{"name":"José González","mbid":"cd8c5019-5d75-4d5c-bc28-e1e26a7dd5c8"}}},{"timestamp":{"iso":"2009-07-12T03:37:37","unixtimestamp":1247369857},"track":{"name":"Don\u0027t See The Sorrow","mbid":"643a022d-8c35-4611-950a-e3a00764816c","artist":{"name":"Au Revoir Simone","mbid":"b6c7127e-9aec-4e02-ba21-cad9c0cb27c1"}},"uncorrectedTrack":{"name":"Don\u0027t See The Sorrow","mbid":"643a022d-8c35-4611-950a-e3a00764816c","artist":{"name":"Au Revoir Simone","mbid":"b6c7127e-9aec-4e02-ba21-cad9c0cb27c1"}},"album":{"name":"The Bird Of Music","mbid":"5dcd7b95-7b30-40b4-ab9b-fda4ea3e2859","artist":{"name":"Au Revoir Simone","mbid":"b6c7127e-9aec-4e02-ba21-cad9c0cb27c1"}}},{"timestamp":{"iso":"2009-07-12T03:42:15","unixtimestamp":1247370135},"track":{"name":"Rise in shame","mbid":"acaf92a1-acf1-4774-aa34-15881176f930","artist":{"name":"Thomas Dybdahl","mbid":"33b4f248-d355-4d9e-bc4d-42f6f82065c8"}},"uncorrectedTrack":{"name":"Rise in shame","mbid":"acaf92a1-acf1-4774-aa34-15881176f930","artist":{"name":"Thomas Dybdahl","mbid":"33b4f248-d355-4d9e-bc4d-42f6f82065c8"}},"album":{"name":"Stray Dogs","mbid":"79e7d819-e3fc-4df0-89ff-4bb732b443c1","artist":{"name":"Thomas Dybdahl","mbid":"33b4f248-d355-4d9e-bc4d-42f6f82065c8"}}},{"timestamp":{"iso":"2009-07-12T03:48:48","unixtimestamp":1247370528},"track":{"name":"A Space Boy Dream","artist":{"name":"Belle and Sebastian","mbid":"6c6011d1-7e13-4ea8-9858-a9b37ece668e"}},"uncorrectedTrack":{"name":"A Space Boy Dream","artist":{"name":"Belle and Sebastian","mbid":"6c6011d1-7e13-4ea8-9858-a9b37ece668e"}},"album":{"name":"The Boy With The Arab Strap","mbid":"0142fbf3-55de-4c4b-9d9f-a0af5a7caff5","artist":{"name":"Belle and Sebastian","mbid":"6c6011d1-7e13-4ea8-9858-a9b37ece668e"}}},{"timestamp":{"iso":"2009-07-12T03:51:58","unixtimestamp":1247370718},"track":{"name":"Rain City","mbid":"162e4dcd-5f9c-4173-8d89-3bd33d355b50","artist":{"name":"Turin Brakes","mbid":"2ecbd923-9daf-4f18-9250-e482ccec4c28"}},"uncorrectedTrack":{"name":"Rain City","mbid":"162e4dcd-5f9c-4173-8d89-3bd33d355b50","artist":{"name":"Turin Brakes","mbid":"2ecbd923-9daf-4f18-9250-e482ccec4c28"}},"album":{"name":"Ether Song","mbid":"16cf9e01-9036-49e4-b0b4-cfc109dead4c","artist":{"name":"Turin Brakes","mbid":"2ecbd923-9daf-4f18-9250-e482ccec4c28"}}},{"timestamp":{"iso":"2009-07-12T03:56:12","unixtimestamp":1247370972},"track":{"name":"Kill The Turkey (Live)","artist":{"name":"Gregory and the Hawk","mbid":"3f180da3-4d5e-4678-957c-15ccdb123d84"}},"uncorrectedTrack":{"name":"Kill The Turkey (Live)","artist":{"name":"Gregory and the Hawk","mbid":"3f180da3-4d5e-4678-957c-15ccdb123d84"}}},{"timestamp":{"iso":"2009-07-12T03:59:42","unixtimestamp":1247371182},"track":{"name":"Before You Cry","mbid":"25bfa57a-607f-4d49-9b3f-a715b97dce2f","artist":{"name":"Camera Obscura","mbid":"5f2e7aab-eb20-469b-ad4a-72deb3eb89e7"}},"uncorrectedTrack":{"name":"Before You Cry","mbid":"25bfa57a-607f-4d49-9b3f-a715b97dce2f","artist":{"name":"Camera Obscura","mbid":"5f2e7aab-eb20-469b-ad4a-72deb3eb89e7"}},"album":{"name":"Underachievers Please Try Harder","mbid":"132e4ef7-8abb-4e41-8019-6d9057f0a440","artist":{"name":"Camera Obscura","mbid":"5f2e7aab-eb20-469b-ad4a-72deb3eb89e7"}}},{"timestamp":{"iso":"2009-07-12T04:02:49","unixtimestamp":1247371369},"track":{"name":"This Love","artist":{"name":"Christos Zarampoukas"}},"uncorrectedTrack":{"name":"This Love","artist":{"name":"Christos Zarampoukas"}},"album":{"name":"White \u0026 Still","artist":{"name":"Christos Zarampoukas"}}},{"timestamp":{"iso":"2009-07-12T04:06:33","unixtimestamp":1247371593},"track":{"name":"Hands Remember","mbid":"56092de2-bb28-48ec-8f1c-b61e31461b97","artist":{"name":"Seabear","mbid":"30f3486e-1def-4fc4-b47b-5283eca9295f"}},"uncorrectedTrack":{"name":"Hands Remember","mbid":"56092de2-bb28-48ec-8f1c-b61e31461b97","artist":{"name":"Seabear","mbid":"30f3486e-1def-4fc4-b47b-5283eca9295f"}},"album":{"name":"The Ghost That Carried Us Away (Offical Morr Music Upload)","artist":{"name":"Seabear","mbid":"30f3486e-1def-4fc4-b47b-5283eca9295f"}}},{"timestamp":{"iso":"2009-07-12T04:10:46","unixtimestamp":1247371846},"track":{"name":"Can\u0027t Go Back Now","mbid":"1d565de7-abc2-4146-b10c-a7584888447d","artist":{"name":"The Weepies","mbid":"01ea7251-fb1d-4af9-8ee6-cf9e5fce657f"}},"uncorrectedTrack":{"name":"Can\u0027t Go Back Now","mbid":"1d565de7-abc2-4146-b10c-a7584888447d","artist":{"name":"The Weepies","mbid":"01ea7251-fb1d-4af9-8ee6-cf9e5fce657f"}},"album":{"name":"Hideaway","mbid":"1606eac8-91d1-4a89-90c0-728432cec91d","artist":{"name":"The Weepies","mbid":"01ea7251-fb1d-4af9-8ee6-cf9e5fce657f"}}},{"timestamp":{"iso":"2009-07-12T04:13:13","unixtimestamp":1247371993},"track":{"name":"Don\u0027t Give Up","mbid":"4b7e3d72-f032-40c6-a11d-ee5bbcb3a9fc","artist":{"name":"The Whitest Boy Alive","mbid":"f83781c8-64f9-4657-85bd-51f74d195cfd"}},"uncorrectedTrack":{"name":"Don\u0027t Give Up","mbid":"4b7e3d72-f032-40c6-a11d-ee5bbcb3a9fc","artist":{"name":"The Whitest Boy Alive","mbid":"f83781c8-64f9-4657-85bd-51f74d195cfd"}},"album":{"name":"Dreams","mbid":"b92cdc4d-84e7-3673-87d2-c833966515e7","artist":{"name":"The Whitest Boy Alive","mbid":"f83781c8-64f9-4657-85bd-51f74d195cfd"}}},{"timestamp":{"iso":"2009-07-12T04:19:11","unixtimestamp":1247372351},"track":{"name":"Quiet \u0026 Still","mbid":"39aaa317-d282-44c0-b9c5-309286296c61","artist":{"name":"Magnet","mbid":"031b4741-e112-4788-9fb6-86dfdbaa5efd"}},"uncorrectedTrack":{"name":"Quiet \u0026 Still","mbid":"39aaa317-d282-44c0-b9c5-309286296c61","artist":{"name":"Magnet","mbid":"031b4741-e112-4788-9fb6-86dfdbaa5efd"}},"album":{"name":"Quiet \u0026 Still","mbid":"072810ab-a8d9-4d8a-89bb-bd28310f79db","artist":{"name":"Magnet","mbid":"031b4741-e112-4788-9fb6-86dfdbaa5efd"}}},{"timestamp":{"iso":"2009-07-12T04:22:56","unixtimestamp":1247372576},"track":{"name":"Consolation Prizes","mbid":"c08b2c20-7216-4454-bbb6-b5cfde751403","artist":{"name":"Phoenix","mbid":"02f4c1ff-65e0-4412-8e8b-6239b0faecb5"}},"uncorrectedTrack":{"name":"Consolation Prizes","mbid":"c08b2c20-7216-4454-bbb6-b5cfde751403","artist":{"name":"Phoenix","mbid":"02f4c1ff-65e0-4412-8e8b-6239b0faecb5"}},"album":{"name":"It\u0027s Never Been Like That","mbid":"d9340711-5c14-4251-a87e-d78bd7c33e1c","artist":{"name":"Phoenix","mbid":"02f4c1ff-65e0-4412-8e8b-6239b0faecb5"}}},{"timestamp":{"iso":"2009-07-12T04:26:18","unixtimestamp":1247372778},"track":{"name":"You\u0027re A Wolf","mbid":"06eeb0dc-4fcb-4ca8-a110-c68751fcccf4","artist":{"name":"Sea Wolf","mbid":"81be1ffb-da44-4449-abdb-40d5b34192f9"}},"uncorrectedTrack":{"name":"You\u0027re A Wolf","mbid":"06eeb0dc-4fcb-4ca8-a110-c68751fcccf4","artist":{"name":"Sea Wolf","mbid":"81be1ffb-da44-4449-abdb-40d5b34192f9"}},"album":{"name":"Leaves in the River","mbid":"1f535139-1a00-4da7-89cc-94cb50ceb44d","artist":{"name":"Sea Wolf","mbid":"81be1ffb-da44-4449-abdb-40d5b34192f9"}}},{"timestamp":{"iso":"2009-07-12T04:30:06","unixtimestamp":1247373006},"track":{"name":"Glass Houses","mbid":"70a84ab2-312c-4d22-b6a1-845e7d27afbd","artist":{"name":"Get Cape. Wear Cape. Fly","mbid":"000d90ec-d64c-48a1-b775-e726fd240e9f"}},"uncorrectedTrack":{"name":"Glass Houses","mbid":"70a84ab2-312c-4d22-b6a1-845e7d27afbd","artist":{"name":"Get Cape. Wear Cape. Fly","mbid":"000d90ec-d64c-48a1-b775-e726fd240e9f"}},"album":{"name":"Get Cape. Wear Cape. Fly EP","mbid":"23b572ae-8922-42d1-b7a3-ac4fd8c9ff16","artist":{"name":"Get Cape. Wear Cape. Fly","mbid":"000d90ec-d64c-48a1-b775-e726fd240e9f"}}},{"timestamp":{"iso":"2009-07-12T04:34:00","unixtimestamp":1247373240},"track":{"name":"Pulling On a Line","mbid":"3daafecd-2bdb-48d7-b537-db5cd0e49ed2","artist":{"name":"Great Lake Swimmers","mbid":"64deac19-021e-4dc1-8d11-658be8763589"}},"uncorrectedTrack":{"name":"Pulling On a Line","mbid":"3daafecd-2bdb-48d7-b537-db5cd0e49ed2","artist":{"name":"Great Lake Swimmers","mbid":"64deac19-021e-4dc1-8d11-658be8763589"}},"album":{"name":"Lost Channels","mbid":"ba4c1df0-ab7d-48e2-aa99-98dd4650708a","artist":{"name":"Great Lake Swimmers","mbid":"64deac19-021e-4dc1-8d11-658be8763589"}}},{"timestamp":{"iso":"2009-07-27T12:54:37","unixtimestamp":1248699277},"track":{"name":"Down on Love","mbid":"dacf19b9-f112-4afc-89a7-eb2b8ca75f12","artist":{"name":"Sarah Blasko","mbid":"fa319aa2-15cb-4d02-8a0b-7080869e43ca"}},"uncorrectedTrack":{"name":"Down on Love","mbid":"dacf19b9-f112-4afc-89a7-eb2b8ca75f12","artist":{"name":"Sarah Blasko","mbid":"fa319aa2-15cb-4d02-8a0b-7080869e43ca"}},"album":{"name":"As Day Follows Night","mbid":"741e401c-6832-486d-acbf-95e6a0634e98","artist":{"name":"Sarah Blasko","mbid":"fa319aa2-15cb-4d02-8a0b-7080869e43ca"}}},{"timestamp":{"iso":"2009-07-27T12:57:08","unixtimestamp":1248699428},"track":{"name":"All I Want","mbid":"7ede9db7-1013-46c0-b9e1-53d0e3324601","artist":{"name":"Sarah Blasko","mbid":"fa319aa2-15cb-4d02-8a0b-7080869e43ca"}},"uncorrectedTrack":{"name":"All I Want","mbid":"7ede9db7-1013-46c0-b9e1-53d0e3324601","artist":{"name":"Sarah Blasko","mbid":"fa319aa2-15cb-4d02-8a0b-7080869e43ca"}},"album":{"name":"As Day Follows Night","mbid":"741e401c-6832-486d-acbf-95e6a0634e98","artist":{"name":"Sarah Blasko","mbid":"fa319aa2-15cb-4d02-8a0b-7080869e43ca"}}},{"timestamp":{"iso":"2009-07-27T13:08:09","unixtimestamp":1248700089},"track":{"name":"Comedy Central Stand-Up: Al Madrigal","artist":{"name":"Comedy Central"}},"uncorrectedTrack":{"name":"Comedy Central Stand-Up: Al Madrigal","artist":{"name":"Comedy Central"}},"album":{"name":"Comedy Central: Stand-Up (Video)","artist":{"name":"Comedy Central"}}},{"timestamp":{"iso":"2009-07-27T13:09:28","unixtimestamp":1248700168},"track":{"name":"Comedy Central Stand-Up: Alonzo Bodden","artist":{"name":"Comedy Central"}},"uncorrectedTrack":{"name":"Comedy Central Stand-Up: Alonzo Bodden","artist":{"name":"Comedy Central"}},"album":{"name":"Comedy Central: Stand-Up (Video)","artist":{"name":"Comedy Central"}}},{"timestamp":{"iso":"2009-07-27T13:10:21","unixtimestamp":1248700221},"track":{"name":"Comedy Central Stand-Up: Aziz Ansari","artist":{"name":"Comedy Central"}},"uncorrectedTrack":{"name":"Comedy Central Stand-Up: Aziz Ansari","artist":{"name":"Comedy Central"}},"album":{"name":"Comedy Central: Stand-Up (Video)","artist":{"name":"Comedy Central"}}},{"timestamp":{"iso":"2009-07-27T13:11:35","unixtimestamp":1248700295},"track":{"name":"Comedy Central Stand-Up: Becky Donohue","artist":{"name":"Comedy Central"}},"uncorrectedTrack":{"name":"Comedy Central Stand-Up: Becky Donohue","artist":{"name":"Comedy Central"}},"album":{"name":"Comedy Central: Stand-Up (Video)","artist":{"name":"Comedy Central"}}},{"timestamp":{"iso":"2009-07-27T13:13:30","unixtimestamp":1248700410},"track":{"name":"Comedy Central Stand-Up: Billy D. Washington","artist":{"name":"Comedy Central"}},"uncorrectedTrack":{"name":"Comedy Central Stand-Up: Billy D. Washington","artist":{"name":"Comedy Central"}},"album":{"name":"Comedy Central: Stand-Up (Video)","artist":{"name":"Comedy Central"}}},{"timestamp":{"iso":"2009-07-27T13:14:02","unixtimestamp":1248700442},"track":{"name":"Comedy Central Stand-Up: Blair Butler","artist":{"name":"Comedy Central"}},"uncorrectedTrack":{"name":"Comedy Central Stand-Up: Blair Butler","artist":{"name":"Comedy Central"}},"album":{"name":"Comedy Central: Stand-Up (Video)","artist":{"name":"Comedy Central"}}},{"timestamp":{"iso":"2009-07-27T13:16:34","unixtimestamp":1248700594},"track":{"name":"Comedy Central Stand-Up: Bonnie McFarlane","artist":{"name":"Comedy Central"}},"uncorrectedTrack":{"name":"Comedy Central Stand-Up: Bonnie McFarlane","artist":{"name":"Comedy Central"}},"album":{"name":"Comedy Central: Stand-Up (Video)","artist":{"name":"Comedy Central"}}},{"timestamp":{"iso":"2009-07-27T13:17:25","unixtimestamp":1248700645},"track":{"name":"Comedy Central Stand-Up: Chris Mata","artist":{"name":"Comedy Central"}},"uncorrectedTrack":{"name":"Comedy Central Stand-Up: Chris Mata","artist":{"name":"Comedy Central"}},"album":{"name":"Comedy Central: Stand-Up (Video)","artist":{"name":"Comedy Central"}}},{"timestamp":{"iso":"2009-07-27T13:19:40","unixtimestamp":1248700780},"track":{"name":"Comedy Central Stand-Up: Damon Williams","artist":{"name":"Comedy Central"}},"uncorrectedTrack":{"name":"Comedy Central Stand-Up: Damon Williams","artist":{"name":"Comedy Central"}},"album":{"name":"Comedy Central: Stand-Up (Video)","artist":{"name":"Comedy Central"}}},{"timestamp":{"iso":"2009-07-27T13:20:49","unixtimestamp":1248700849},"track":{"name":"Comedy Central Stand-Up: Dan Gabriel","artist":{"name":"Comedy Central"}},"uncorrectedTrack":{"name":"Comedy Central Stand-Up: Dan Gabriel","artist":{"name":"Comedy Central"}},"album":{"name":"Comedy Central: Stand-Up (Video)","artist":{"name":"Comedy Central"}}},{"timestamp":{"iso":"2009-07-27T13:22:00","unixtimestamp":1248700920},"track":{"name":"Comedy Central Stand-Up: Danielle Koenig","artist":{"name":"Comedy Central"}},"uncorrectedTrack":{"name":"Comedy Central Stand-Up: Danielle Koenig","artist":{"name":"Comedy Central"}},"album":{"name":"Comedy Central: Stand-Up (Video)","artist":{"name":"Comedy Central"}}},{"timestamp":{"iso":"2009-07-27T13:22:49","unixtimestamp":1248700969},"track":{"name":"Comedy Central Stand-Up: Debbie Shea","artist":{"name":"Comedy Central"}},"uncorrectedTrack":{"name":"Comedy Central Stand-Up: Debbie Shea","artist":{"name":"Comedy Central"}},"album":{"name":"Comedy Central: Stand-Up (Video)","artist":{"name":"Comedy Central"}}},{"timestamp":{"iso":"2009-07-27T13:27:03","unixtimestamp":1248701223},"track":{"name":"Comedy Central Stand-Up: Donnell Rawlings","artist":{"name":"Comedy Central"}},"uncorrectedTrack":{"name":"Comedy Central Stand-Up: Donnell Rawlings","artist":{"name":"Comedy Central"}},"album":{"name":"Comedy Central: Stand-Up (Video)","artist":{"name":"Comedy Central"}}},{"timestamp":{"iso":"2009-07-27T13:27:52","unixtimestamp":1248701272},"track":{"name":"Comedy Central Stand-Up: Eddie Gossling - Math","artist":{"name":"Comedy Central"}},"uncorrectedTrack":{"name":"Comedy Central Stand-Up: Eddie Gossling - Math","artist":{"name":"Comedy Central"}},"album":{"name":"Comedy Central: Stand-Up (Video)","artist":{"name":"Comedy Central"}}},{"timestamp":{"iso":"2009-07-27T13:29:51","unixtimestamp":1248701391},"track":{"name":"Comedy Central Stand-Up: Eddie Gossling","artist":{"name":"Comedy Central"}},"uncorrectedTrack":{"name":"Comedy Central Stand-Up: Eddie Gossling","artist":{"name":"Comedy Central"}},"album":{"name":"Comedy Central: Stand-Up (Video)","artist":{"name":"Comedy Central"}}},{"timestamp":{"iso":"2009-07-27T13:30:45","unixtimestamp":1248701445},"track":{"name":"Comedy Central Stand-Up: Eliot Chang","artist":{"name":"Comedy Central"}},"uncorrectedTrack":{"name":"Comedy Central Stand-Up: Eliot Chang","artist":{"name":"Comedy Central"}},"album":{"name":"Comedy Central: Stand-Up (Video)","artist":{"name":"Comedy Central"}}},{"timestamp":{"iso":"2009-07-27T13:32:06","unixtimestamp":1248701526},"track":{"name":"Comedy Central Stand-Up: Erin Foley","artist":{"name":"Comedy Central"}},"uncorrectedTrack":{"name":"Comedy Central Stand-Up: Erin Foley","artist":{"name":"Comedy Central"}},"album":{"name":"Comedy Central: Stand-Up (Video)","artist":{"name":"Comedy Central"}}},{"timestamp":{"iso":"2009-07-27T13:33:11","unixtimestamp":1248701591},"track":{"name":"Comedy Central Stand-Up: Fred Armisen","artist":{"name":"Comedy Central"}},"uncorrectedTrack":{"name":"Comedy Central Stand-Up: Fred Armisen","artist":{"name":"Comedy Central"}},"album":{"name":"Comedy Central: Stand-Up (Video)","artist":{"name":"Comedy Central"}}},{"timestamp":{"iso":"2009-07-27T13:34:02","unixtimestamp":1248701642},"track":{"name":"Comedy Central Stand-Up: Gabriel Iglesias - Mall Maps","artist":{"name":"Comedy Central"}},"uncorrectedTrack":{"name":"Comedy Central Stand-Up: Gabriel Iglesias - Mall Maps","artist":{"name":"Comedy Central"}},"album":{"name":"Comedy Central: Stand-Up (Video)","artist":{"name":"Comedy Central"}}},{"timestamp":{"iso":"2009-07-27T13:36:04","unixtimestamp":1248701764},"track":{"name":"Comedy Central Stand-Up: Greg Warren","artist":{"name":"Comedy Central"}},"uncorrectedTrack":{"name":"Comedy Central Stand-Up: Greg Warren","artist":{"name":"Comedy Central"}},"album":{"name":"Comedy Central: Stand-Up (Video)","artist":{"name":"Comedy Central"}}},{"timestamp":{"iso":"2009-07-27T13:37:38","unixtimestamp":1248701858},"track":{"name":"Comedy Central Stand-Up: Hot Picks","artist":{"name":"Comedy Central"}},"uncorrectedTrack":{"name":"Comedy Central Stand-Up: Hot Picks","artist":{"name":"Comedy Central"}},"album":{"name":"Comedy Central: Stand-Up (Video)","artist":{"name":"Comedy Central"}}},{"timestamp":{"iso":"2009-07-27T13:56:07","unixtimestamp":1248702967},"track":{"name":"Comedy Central Stand-Up: James Johann","artist":{"name":"Comedy Central"}},"uncorrectedTrack":{"name":"Comedy Central Stand-Up: James Johann","artist":{"name":"Comedy Central"}},"album":{"name":"Comedy Central: Stand-Up (Video)","artist":{"name":"Comedy Central"}}},{"timestamp":{"iso":"2009-07-27T13:59:39","unixtimestamp":1248703179},"track":{"name":"Comedy Central Stand-Up: Janine DiTullio","artist":{"name":"Comedy Central"}},"uncorrectedTrack":{"name":"Comedy Central Stand-Up: Janine DiTullio","artist":{"name":"Comedy Central"}},"album":{"name":"Comedy Central: Stand-Up (Video)","artist":{"name":"Comedy Central"}}},{"timestamp":{"iso":"2009-07-27T14:00:44","unixtimestamp":1248703244},"track":{"name":"Comedy Central Stand-Up: Jessica Kirson - Cake","artist":{"name":"Comedy Central"}},"uncorrectedTrack":{"name":"Comedy Central Stand-Up: Jessica Kirson - Cake","artist":{"name":"Comedy Central"}},"album":{"name":"Comedy Central: Stand-Up (Video)","artist":{"name":"Comedy Central"}}},{"timestamp":{"iso":"2009-07-27T14:02:12","unixtimestamp":1248703332},"track":{"name":"Comedy Central Stand-Up: Kristeen von Hagen","artist":{"name":"Comedy Central"}},"uncorrectedTrack":{"name":"Comedy Central Stand-Up: Kristeen von Hagen","artist":{"name":"Comedy Central"}},"album":{"name":"Comedy Central: Stand-Up (Video)","artist":{"name":"Comedy Central"}}},{"timestamp":{"iso":"2009-07-27T14:03:07","unixtimestamp":1248703387},"track":{"name":"Comedy Central Stand-Up: Lisa Gopman","artist":{"name":"Comedy Central"}},"uncorrectedTrack":{"name":"Comedy Central Stand-Up: Lisa Gopman","artist":{"name":"Comedy Central"}},"album":{"name":"Comedy Central: Stand-Up (Video)","artist":{"name":"Comedy Central"}}},{"timestamp":{"iso":"2009-07-27T14:03:51","unixtimestamp":1248703431},"track":{"name":"Comedy Central Stand-Up: Megan Mooney","artist":{"name":"Comedy Central"}},"uncorrectedTrack":{"name":"Comedy Central Stand-Up: Megan Mooney","artist":{"name":"Comedy Central"}},"album":{"name":"Comedy Central: Stand-Up (Video)","artist":{"name":"Comedy Central"}}},{"timestamp":{"iso":"2009-07-27T14:04:47","unixtimestamp":1248703487},"track":{"name":"Comedy Central Stand-Up: Michael Somerville","artist":{"name":"Comedy Central"}},"uncorrectedTrack":{"name":"Comedy Central Stand-Up: Michael Somerville","artist":{"name":"Comedy Central"}},"album":{"name":"Comedy Central: Stand-Up (Video)","artist":{"name":"Comedy Central"}}},{"timestamp":{"iso":"2009-07-27T14:06:17","unixtimestamp":1248703577},"track":{"name":"Comedy Central Stand-Up: Michelle Biloon","artist":{"name":"Comedy Central"}},"uncorrectedTrack":{"name":"Comedy Central Stand-Up: Michelle Biloon","artist":{"name":"Comedy Central"}},"album":{"name":"Comedy Central: Stand-Up (Video)","artist":{"name":"Comedy Central"}}},{"timestamp":{"iso":"2009-07-27T14:09:02","unixtimestamp":1248703742},"track":{"name":"Comedy Central Stand-Up: Natasha Leggero","artist":{"name":"Comedy Central"}},"uncorrectedTrack":{"name":"Comedy Central Stand-Up: Natasha Leggero","artist":{"name":"Comedy Central"}},"album":{"name":"Comedy Central: Stand-Up (Video)","artist":{"name":"Comedy Central"}}},{"timestamp":{"iso":"2009-07-27T14:10:24","unixtimestamp":1248703824},"track":{"name":"Comedy Central Stand-Up: Rachel Feinstein","artist":{"name":"Comedy Central"}},"uncorrectedTrack":{"name":"Comedy Central Stand-Up: Rachel Feinstein","artist":{"name":"Comedy Central"}},"album":{"name":"Comedy Central: Stand-Up (Video)","artist":{"name":"Comedy Central"}}},{"timestamp":{"iso":"2009-07-27T14:16:51","unixtimestamp":1248704211},"track":{"name":"Comedy Central Stand-Up: Rob Pue","artist":{"name":"Comedy Central"}},"uncorrectedTrack":{"name":"Comedy Central Stand-Up: Rob Pue","artist":{"name":"Comedy Central"}},"album":{"name":"Comedy Central: Stand-Up (Video)","artist":{"name":"Comedy Central"}}},{"timestamp":{"iso":"2009-07-27T14:24:06","unixtimestamp":1248704646},"track":{"name":"Comedy Central Stand-Up: Todd Lynn","artist":{"name":"Comedy Central"}},"uncorrectedTrack":{"name":"Comedy Central Stand-Up: Todd Lynn","artist":{"name":"Comedy Central"}},"album":{"name":"Comedy Central: Stand-Up (Video)","artist":{"name":"Comedy Central"}}},{"timestamp":{"iso":"2009-07-28T13:14:05","unixtimestamp":1248786845},"track":{"name":"ITC.SO-Episode62-2009.07.21","artist":{"name":"Jeff Atwood and Joel Spolsky"}},"uncorrectedTrack":{"name":"ITC.SO-Episode62-2009.07.21","artist":{"name":"Jeff Atwood and Joel Spolsky"}},"album":{"name":"The StackOverflow Podcast","artist":{"name":"Jeff Atwood and Joel Spolsky"}}},{"timestamp":{"iso":"2009-07-31T02:13:30","unixtimestamp":1249006410},"track":{"name":"Little Plastic Castle","mbid":"1d8bb3c8-e111-4ad8-ae1f-30b61a1e041d","artist":{"name":"Ani DiFranco","mbid":"a7bdc71f-697a-45d9-92b2-a01fbbe50272"}},"uncorrectedTrack":{"name":"Little Plastic Castles","artist":{"name":"Ani DiFranco","mbid":"a7bdc71f-697a-45d9-92b2-a01fbbe50272"}},"album":{"name":"Little Plastic Castles","artist":{"name":"Ani DiFranco","mbid":"a7bdc71f-697a-45d9-92b2-a01fbbe50272"}}},{"timestamp":{"iso":"2009-07-31T02:17:34","unixtimestamp":1249006654},"track":{"name":"Fuel","mbid":"2398d33a-a094-4dd6-8d84-efc4177aaf4e","artist":{"name":"Ani DiFranco","mbid":"a7bdc71f-697a-45d9-92b2-a01fbbe50272"}},"uncorrectedTrack":{"name":"Fuel","mbid":"2398d33a-a094-4dd6-8d84-efc4177aaf4e","artist":{"name":"Ani DiFranco","mbid":"a7bdc71f-697a-45d9-92b2-a01fbbe50272"}},"album":{"name":"Little Plastic Castles","artist":{"name":"Ani DiFranco","mbid":"a7bdc71f-697a-45d9-92b2-a01fbbe50272"}}},{"timestamp":{"iso":"2009-07-31T02:21:35","unixtimestamp":1249006895},"track":{"name":"Gravel","mbid":"cdcafbab-771d-4b7d-84ab-f800cb94ca9f","artist":{"name":"Ani DiFranco","mbid":"a7bdc71f-697a-45d9-92b2-a01fbbe50272"}},"uncorrectedTrack":{"name":"Gravel","mbid":"cdcafbab-771d-4b7d-84ab-f800cb94ca9f","artist":{"name":"Ani DiFranco","mbid":"a7bdc71f-697a-45d9-92b2-a01fbbe50272"}},"album":{"name":"Little Plastic Castles","artist":{"name":"Ani DiFranco","mbid":"a7bdc71f-697a-45d9-92b2-a01fbbe50272"}}},{"timestamp":{"iso":"2009-07-31T02:25:07","unixtimestamp":1249007107},"track":{"name":"As Is","mbid":"ab85ae33-74cc-4e39-998c-e9e6796f78e0","artist":{"name":"Ani DiFranco","mbid":"a7bdc71f-697a-45d9-92b2-a01fbbe50272"}},"uncorrectedTrack":{"name":"As Is","mbid":"ab85ae33-74cc-4e39-998c-e9e6796f78e0","artist":{"name":"Ani DiFranco","mbid":"a7bdc71f-697a-45d9-92b2-a01fbbe50272"}},"album":{"name":"Little Plastic Castles","artist":{"name":"Ani DiFranco","mbid":"a7bdc71f-697a-45d9-92b2-a01fbbe50272"}}},{"timestamp":{"iso":"2009-07-31T02:29:13","unixtimestamp":1249007353},"track":{"name":"Two Little Girls","mbid":"64524acb-fc73-47e4-adc2-d9748a6931e4","artist":{"name":"Ani DiFranco","mbid":"a7bdc71f-697a-45d9-92b2-a01fbbe50272"}},"uncorrectedTrack":{"name":"Two Little Girls","mbid":"64524acb-fc73-47e4-adc2-d9748a6931e4","artist":{"name":"Ani DiFranco","mbid":"a7bdc71f-697a-45d9-92b2-a01fbbe50272"}},"album":{"name":"Little Plastic Castles","artist":{"name":"Ani DiFranco","mbid":"a7bdc71f-697a-45d9-92b2-a01fbbe50272"}}},{"timestamp":{"iso":"2009-07-31T02:34:11","unixtimestamp":1249007651},"track":{"name":"Deep Dish","mbid":"b663d61e-f15a-4969-887e-3e2168a89d74","artist":{"name":"Ani DiFranco","mbid":"a7bdc71f-697a-45d9-92b2-a01fbbe50272"}},"uncorrectedTrack":{"name":"Deep Dish","mbid":"b663d61e-f15a-4969-887e-3e2168a89d74","artist":{"name":"Ani DiFranco","mbid":"a7bdc71f-697a-45d9-92b2-a01fbbe50272"}},"album":{"name":"Little Plastic Castles","artist":{"name":"Ani DiFranco","mbid":"a7bdc71f-697a-45d9-92b2-a01fbbe50272"}}},{"timestamp":{"iso":"2009-07-31T02:37:48","unixtimestamp":1249007868},"track":{"name":"Loom","mbid":"9d6b099e-6804-4735-9676-75a9f0933dc9","artist":{"name":"Ani DiFranco","mbid":"a7bdc71f-697a-45d9-92b2-a01fbbe50272"}},"uncorrectedTrack":{"name":"Loom","mbid":"9d6b099e-6804-4735-9676-75a9f0933dc9","artist":{"name":"Ani DiFranco","mbid":"a7bdc71f-697a-45d9-92b2-a01fbbe50272"}},"album":{"name":"Little Plastic Castles","artist":{"name":"Ani DiFranco","mbid":"a7bdc71f-697a-45d9-92b2-a01fbbe50272"}}},{"timestamp":{"iso":"2009-07-31T02:40:39","unixtimestamp":1249008039},"track":{"name":"Pixie","mbid":"f752f530-f813-469e-b53b-94dc0038eea7","artist":{"name":"Ani DiFranco","mbid":"a7bdc71f-697a-45d9-92b2-a01fbbe50272"}},"uncorrectedTrack":{"name":"Pixie","mbid":"f752f530-f813-469e-b53b-94dc0038eea7","artist":{"name":"Ani DiFranco","mbid":"a7bdc71f-697a-45d9-92b2-a01fbbe50272"}},"album":{"name":"Little Plastic Castles","artist":{"name":"Ani DiFranco","mbid":"a7bdc71f-697a-45d9-92b2-a01fbbe50272"}}},{"timestamp":{"iso":"2009-07-31T02:45:04","unixtimestamp":1249008304},"track":{"name":"Swan Dive","mbid":"ffec27c9-b992-4366-9c80-a1609b69693c","artist":{"name":"Ani DiFranco","mbid":"a7bdc71f-697a-45d9-92b2-a01fbbe50272"}},"uncorrectedTrack":{"name":"Swan Dive","mbid":"ffec27c9-b992-4366-9c80-a1609b69693c","artist":{"name":"Ani DiFranco","mbid":"a7bdc71f-697a-45d9-92b2-a01fbbe50272"}},"album":{"name":"Little Plastic Castles","artist":{"name":"Ani DiFranco","mbid":"a7bdc71f-697a-45d9-92b2-a01fbbe50272"}}},{"timestamp":{"iso":"2009-07-31T02:51:34","unixtimestamp":1249008694},"track":{"name":"Glass House","mbid":"44090631-b6ac-4786-87c2-6cd83f854e3c","artist":{"name":"Ani DiFranco","mbid":"a7bdc71f-697a-45d9-92b2-a01fbbe50272"}},"uncorrectedTrack":{"name":"Glass House","mbid":"44090631-b6ac-4786-87c2-6cd83f854e3c","artist":{"name":"Ani DiFranco","mbid":"a7bdc71f-697a-45d9-92b2-a01fbbe50272"}},"album":{"name":"Little Plastic Castles","artist":{"name":"Ani DiFranco","mbid":"a7bdc71f-697a-45d9-92b2-a01fbbe50272"}}},{"timestamp":{"iso":"2009-07-31T02:56:54","unixtimestamp":1249009014},"track":{"name":"Independence Day","mbid":"5d94f5ef-8801-46f3-b194-fc03c3319f33","artist":{"name":"Ani DiFranco","mbid":"a7bdc71f-697a-45d9-92b2-a01fbbe50272"}},"uncorrectedTrack":{"name":"Independence Day","mbid":"5d94f5ef-8801-46f3-b194-fc03c3319f33","artist":{"name":"Ani DiFranco","mbid":"a7bdc71f-697a-45d9-92b2-a01fbbe50272"}},"album":{"name":"Little Plastic Castles","artist":{"name":"Ani DiFranco","mbid":"a7bdc71f-697a-45d9-92b2-a01fbbe50272"}}},{"timestamp":{"iso":"2009-07-31T03:00:43","unixtimestamp":1249009243},"track":{"name":"Pulse","mbid":"3a4fd9dd-9330-4563-a0c6-7f461d403b53","artist":{"name":"Ani DiFranco","mbid":"a7bdc71f-697a-45d9-92b2-a01fbbe50272"}},"uncorrectedTrack":{"name":"Pulse","mbid":"3a4fd9dd-9330-4563-a0c6-7f461d403b53","artist":{"name":"Ani DiFranco","mbid":"a7bdc71f-697a-45d9-92b2-a01fbbe50272"}},"album":{"name":"Little Plastic Castles","artist":{"name":"Ani DiFranco","mbid":"a7bdc71f-697a-45d9-92b2-a01fbbe50272"}}}]